tests/tmp/nand2_d.vhd
-- generated automatically

library ieee;
use ieee.std_logic_1164.all;
use ieee.numeric_std.all;

entity nand2_d is
  generic(delay : time := 1000 fs);
  port (
		i0 : in  std_logic;
		i1 : in  std_logic;
		o0 : out  std_logic
  );
end nand2_d;

architecture bhv of nand2_d is
begin
  o0 <= not(i0 and i1) after delay;
end architecture;

tests/tmp/or2_d.vhd
--generated automatically
library ieee;
use ieee.std_logic_1164.all;
use ieee.numeric_std.all;
 
entity or2_d is
		generic(delay : time := 1 ps);
		port(
				i0 : in  std_logic;
				i1 : in  std_logic;
				o0 : out std_logic
		);
end or2_d;
 
architecture rtl of or2_d is
begin
		o0 <=  i0 or i1 after delay;
end rtl;

tests/tmp/xor2_d.vhd
--generated automatically
library ieee;
use ieee.std_logic_1164.all;
use ieee.numeric_std.all;
 
entity xor2_d is
		generic(delay : time := 1 ps);
		port(
				i0 : in  std_logic;
				i1 : in  std_logic;
				o0 : out std_logic
		);
end xor2_d;
 
architecture rtl of xor2_d is
begin
		o0 <= i0 xor i1 after delay;
end rtl;

tests/tmp/and2_d.vhd
--generated automatically
library ieee;
use ieee.std_logic_1164.all;
use ieee.numeric_std.all;
 
entity and2_d is
		generic(delay : time := 1 ps);
		port(
				i0 : in  std_logic;
				i1 : in  std_logic;
				o0 : out std_logic
		);
end and2_d;
 
architecture rtl of and2_d is
begin
		o0 <= i0 and i1 after delay;
end rtl;

tests/tmp/not_d.vhd
--generated automatically
library ieee;
use ieee.std_logic_1164.all;
use ieee.numeric_std.all;
 
entity not_d is
		generic(delay : time := 1 ps);
		port(
				i0 : in  std_logic;
				o0 : out std_logic
		);
end not_d;
 
architecture rtl of not_d is
begin
		o0 <=  not i0 after delay;
end rtl;

tests/tmp/circ_source.vhd
library ieee;
use ieee.std_logic_1164.all;
use ieee.numeric_std.all;
 
library gtech_lib;
 
entity circ_source is
	port(
		i0 : in  std_logic;
		i1 : in  std_logic;
		i2 : in  std_logic;
		i3 : in  std_logic;
		i4 : in  std_logic;
		o0 : out std_logic
	);
end circ_source;
 
architecture netenos of circ_source is
	signal Not140_o0 : std_logic;
	signal Xor2160_o0 : std_logic;
	signal Xor2180_o0 : std_logic;
	signal Or2200_o0 : std_logic;
	signal Xor2220_o0 : std_logic;
	signal Nand2240_o0 : std_logic;
	signal And2260_o0 : std_logic;
	signal Or2280_o0 : std_logic;
	signal Xor2300_o0 : std_logic;
	signal Nand2320_o0 : std_logic;
	signal Or2340_o0 : std_logic;
	signal Nand2360_o0 : std_logic;
	signal Nand2380_o0 : std_logic;
	signal Nand2400_o0 : std_logic;
begin
	----------------------------------
	-- Components interconnect 
	----------------------------------
	Not140 : entity gtech_lib.not_d
		generic map(2000 fs)
		port map(
			i0 => i0,
			o0 => Not140_o0
		);
		Xor2160 : entity gtech_lib.xor2_d
		generic map(5000 fs)
		port map(
			i0 => i3,
			i1 => i4,
			o0 => Xor2160_o0
		);
		Xor2180 : entity gtech_lib.xor2_d
		generic map(5000 fs)
		port map(
			i0 => i1,
			i1 => i2,
			o0 => Xor2180_o0
		);
		Or2200 : entity gtech_lib.or2_d
		generic map(3000 fs)
		port map(
			i0 => Not140_o0,
			i1 => Xor2180_o0,
			o0 => Or2200_o0
		);
		Xor2220 : entity gtech_lib.xor2_d
		generic map(5000 fs)
		port map(
			i0 => i1,
			i1 => i2,
			o0 => Xor2220_o0
		);
		Nand2240 : entity gtech_lib.nand2_d
		generic map(4000 fs)
		port map(
			i0 => Not140_o0,
			i1 => Xor2220_o0,
			o0 => Nand2240_o0
		);
		And2260 : entity gtech_lib.and2_d
		generic map(3000 fs)
		port map(
			i0 => Or2200_o0,
			i1 => Nand2240_o0,
			o0 => And2260_o0
		);
		Or2280 : entity gtech_lib.or2_d
		generic map(3000 fs)
		port map(
			i0 => Xor2160_o0,
			i1 => And2260_o0,
			o0 => Or2280_o0
		);
		Xor2300 : entity gtech_lib.xor2_d
		generic map(5000 fs)
		port map(
			i0 => i3,
			i1 => i4,
			o0 => Xor2300_o0
		);
		Nand2320 : entity gtech_lib.nand2_d
		generic map(4000 fs)
		port map(
			i0 => i0,
			i1 => Xor2220_o0,
			o0 => Nand2320_o0
		);
		Or2340 : entity gtech_lib.or2_d
		generic map(3000 fs)
		port map(
			i0 => i0,
			i1 => Xor2180_o0,
			o0 => Or2340_o0
		);
		Nand2360 : entity gtech_lib.nand2_d
		generic map(4000 fs)
		port map(
			i0 => Nand2320_o0,
			i1 => Or2340_o0,
			o0 => Nand2360_o0
		);
		Nand2380 : entity gtech_lib.nand2_d
		generic map(4000 fs)
		port map(
			i0 => Xor2300_o0,
			i1 => Nand2360_o0,
			o0 => Nand2380_o0
		);
		Nand2400 : entity gtech_lib.nand2_d
		generic map(4000 fs)
		port map(
			i0 => Or2280_o0,
			i1 => Nand2380_o0,
			o0 => Nand2400_o0
		);
	----------------------------------
	-- Wiring primary ouputs 
	----------------------------------
	o0 <= Nand2400_o0;
end netenos;

tests/tmp/circ_source_1_tb.vhd
library ieee;
use ieee.std_logic_1164.all;
use ieee.numeric_std.all;
-- use ieee.std_logic_textio.all;

library std;
use std.textio.all;

entity circ_source_1_tb is
end entity circ_source_1_tb;

architecture netenos of circ_source_1_tb is

    constant unit_delay : time := 1 ps;
    constant nom_period : time := (unit_delay * 10.5);

    signal tb_in : std_logic_vector(4 downto 0);
    
    signal tb_out : std_logic_vector(0 downto 0);
   

    signal tb_o0 : std_logic; 
	signal tb_o0_s : std_logic;
	

    signal running : boolean := true;
    -- signal phase_shift : boolean := false;

begin

    uut : entity work.circ_source(netenos)
    port map (
               tb_in(0), 
       tb_in(1), 
       tb_in(2), 
       tb_in(3), 
       tb_in(4), 
       tb_out(0)
    );

    stim : process
       
    begin

        
        wait for 0.0 * unit_delay;
        tb_in(1) <= '0';
    
        wait for 0.0 * unit_delay;
        tb_in(2) <= '1';
    
        wait for 0.5 * unit_delay;
        tb_in(1) <= '0';
    
        wait for 0.0 * unit_delay;
        tb_in(2) <= '1';
    
        wait for 0.5 * unit_delay;
        tb_in(1) <= '0';
    
        wait for 0.0 * unit_delay;
        tb_in(2) <= '1';
    
        wait for 0.5 * unit_delay;
        tb_in(1) <= '0';
    
        wait for 0.0 * unit_delay;
        tb_in(2) <= '0';
    
        wait for 1.0 * unit_delay;
        tb_in(0) <= '1';
    
        wait for 0.0 * unit_delay;
        tb_in(0) <= '1';
    
        wait for 0.5 * unit_delay;
        tb_in(0) <= '1';
    
        wait for 0.0 * unit_delay;
        tb_in(0) <= '1';
    
        wait for 1.0 * unit_delay;
        tb_in(3) <= '0';
    
        wait for 0.0 * unit_delay;
        tb_in(4) <= '0';
    
        wait for 0.5 * unit_delay;
        tb_in(3) <= '0';
    
        wait for 0.0 * unit_delay;
        tb_in(4) <= '0';
     

        wait for nom_period;
        running <= false;
        -- report "Stopping simulation";
        wait;
    end process;

end architecture netenos;

tests/tmp/circ_source_1_tb.vcd
$date
  Fri Oct  4 18:16:13 2024
$end
$version
  GHDL v0
$end
$timescale
  1 fs
$end
$scope module circ_source_1_tb $end
$var reg 5 ! tb_in[4:0] $end
$var reg 1 " tb_out[0:0] $end
$var reg 1 # tb_o0 $end
$var reg 1 $ tb_o0_s $end
$var reg 1 % running $end
$scope module uut $end
$var reg 1 & i0 $end
$var reg 1 ' i1 $end
$var reg 1 ( i2 $end
$var reg 1 ) i3 $end
$var reg 1 * i4 $end
$var reg 1 + o0 $end
$var reg 1 , not140_o0 $end
$var reg 1 - xor2160_o0 $end
$var reg 1 . xor2180_o0 $end
$var reg 1 / or2200_o0 $end
$var reg 1 0 xor2220_o0 $end
$var reg 1 1 nand2240_o0 $end
$var reg 1 2 and2260_o0 $end
$var reg 1 3 or2280_o0 $end
$var reg 1 4 xor2300_o0 $end
$var reg 1 5 nand2320_o0 $end
$var reg 1 6 or2340_o0 $end
$var reg 1 7 nand2360_o0 $end
$var reg 1 8 nand2380_o0 $end
$var reg 1 9 nand2400_o0 $end
$upscope $end
$upscope $end
$enddefinitions $end
#0
bUU10U !
bU "
U#
U$
1%
U&
0'
1(
U)
U*
U+
U,
U-
U.
U/
U0
U1
U2
U3
U4
U5
U6
U7
U8
U9
#500
#1000
#1500
bUU00U !
0(
#2000
#2500
bUU001 !
1&
#3000
#3500
0,
#4000
b00001 !
0)
0*
0.
00
16
#4500
#5500
0/
11
#6000
15
#6500
0-
04
#7000
02
#8000
07
#8500
03
18
#10000
#10500
b1 "
1+
19
#15000
0%
