tests/tmp/nand2_d.vhd
-- generated automatically

library ieee;
use ieee.std_logic_1164.all;
use ieee.numeric_std.all;

entity nand2_d is
  generic(delay : time := 1000 fs);
  port (
		i0 : in  std_logic;
		i1 : in  std_logic;
		o0 : out  std_logic
  );
end nand2_d;

architecture bhv of nand2_d is
begin
  o0 <= not(i0 and i1) after delay;
end architecture;

tests/tmp/circ_C17.vhd
library ieee;
use ieee.std_logic_1164.all;
use ieee.numeric_std.all;
 
library gtech_lib;
 
entity circ_C17 is
	port(
		i0 : in  std_logic;
		i1 : in  std_logic;
		i2 : in  std_logic;
		i3 : in  std_logic;
		i4 : in  std_logic;
		o0 : out std_logic;
		o1 : out std_logic
	);
end circ_C17;
 
architecture netenos of circ_C17 is
	signal Nand260_o0 : std_logic;
	signal Nand280_o0 : std_logic;
	signal Nand2100_o0 : std_logic;
	signal Nand2120_o0 : std_logic;
	signal Nand2140_o0 : std_logic;
	signal Nand2160_o0 : std_logic;
begin
	----------------------------------
	-- Components interconnect 
	----------------------------------
	Nand260 : entity gtech_lib.nand2_d
		generic map(1000 fs)
		port map(
			i0 => i0,
			i1 => i2,
			o0 => Nand260_o0
		);
		Nand280 : entity gtech_lib.nand2_d
		generic map(1000 fs)
		port map(
			i0 => i2,
			i1 => i3,
			o0 => Nand280_o0
		);
		Nand2100 : entity gtech_lib.nand2_d
		generic map(1000 fs)
		port map(
			i0 => i1,
			i1 => Nand280_o0,
			o0 => Nand2100_o0
		);
		Nand2120 : entity gtech_lib.nand2_d
		generic map(1000 fs)
		port map(
			i0 => Nand260_o0,
			i1 => Nand2100_o0,
			o0 => Nand2120_o0
		);
		Nand2140 : entity gtech_lib.nand2_d
		generic map(1000 fs)
		port map(
			i0 => i4,
			i1 => Nand280_o0,
			o0 => Nand2140_o0
		);
		Nand2160 : entity gtech_lib.nand2_d
		generic map(1000 fs)
		port map(
			i0 => Nand2100_o0,
			i1 => Nand2140_o0,
			o0 => Nand2160_o0
		);
	----------------------------------
	-- Wiring primary ouputs 
	----------------------------------
	o0 <= Nand2120_o0;
	o1 <= Nand2160_o0;
end netenos;

tests/tmp/circ_C17_1_tb.vhd
library ieee;
use ieee.std_logic_1164.all;
use ieee.numeric_std.all;
-- use ieee.std_logic_textio.all;

library std;
use std.textio.all;


entity circ_C17_1_tb is
end entity circ_C17_1_tb;

architecture netenos of circ_C17_1_tb is

    constant unit_delay : time := 1 ps; -- default already is 1, thus this line is not mandatory
    -- With a 1-unit model, the maximum path length is equivalent to the minimal period for nominal behavior 
    -- Which means minimum period is 4 for a unit_delay value of 1 (default value) 
    constant nom_period : time := (unit_delay * 6.0);
    constant obs_period : time := (unit_delay * 6.0);
    constant phase : time := 0.0 ps;
    signal nom_clk : std_logic := '1';
    signal obs_clk : std_logic := '1';

    signal tb_in : std_logic_vector(4 downto 0);
    signal tb_out : std_logic_vector(1 downto 0);
    signal tb_o0 : std_logic; 
	signal tb_o0_s : std_logic;
	signal tb_o1 : std_logic; 
	signal tb_o1_s : std_logic;
	

    signal running : boolean := true;
    signal phase_shift : boolean := false;

begin

    uut : entity work.circ_C17(netenos)
    port map (
       tb_in(0), 
       tb_in(1), 
       tb_in(2), 
       tb_in(3), 
       tb_in(4), 
       tb_out(0), 
       tb_out(1)
    );
    
    phase_shift <= true after phase;
    nom_clk <= not(nom_clk) after (nom_period/2) when running else nom_clk;
    obs_clk <= not(obs_clk) after (obs_period/2) when running and phase_shift else obs_clk;
        
    tb_o0 <= tb_out(0);
	tb_o1 <= tb_out(1);
	

    process(obs_clk)
    begin
        if rising_edge(obs_clk) then
            tb_o0_s <= tb_out(0);
			tb_o1_s <= tb_out(1);
			
        else
            tb_o0_s <= tb_o0_s;
			tb_o1_s <= tb_o1_s;
			
        end if;
    end process;

    stim : process
        file text_file : text open read_mode is "stim.txt";
        variable text_line : line;
        variable stim_val : std_logic_vector(4 downto 0);
        variable text_val : natural;
    begin
        -- report "Starting simulation...";
        
        while not endfile(text_file) loop
            
            readline(text_file, text_line);
           
            -- Skip empty lines and single-line comments
            if text_line.all'length = 0 or text_line.all(1) = '#' then
              next;
            end if;
            
            read(text_line, text_val);
            
            stim_val :=  std_logic_vector(to_unsigned(text_val, 5));
            --read(text_line, stim_val);

            for k in 0 to 4 loop
                tb_in(k) <= stim_val(k);
            end loop;

            wait until rising_edge(nom_clk);
        
        end loop;

        wait for nom_period;
        running <= false;
        -- report "Stopping simulation";
        wait;
    end process;

end architecture netenos;

tests/tmp/circ_C17_1_tb.vcd
$date
  Thu Oct  3 17:17:01 2024
$end
$version
  GHDL v0
$end
$timescale
  1 fs
$end
$scope module circ_c17_1_tb $end
$var reg 1 ! nom_clk $end
$var reg 1 " obs_clk $end
$var reg 5 # tb_in[4:0] $end
$var reg 2 $ tb_out[1:0] $end
$var reg 1 % tb_o0 $end
$var reg 1 & tb_o0_s $end
$var reg 1 ' tb_o1 $end
$var reg 1 ( tb_o1_s $end
$var reg 1 ) running $end
$var reg 1 * phase_shift $end
$scope module uut $end
$var reg 1 + i0 $end
$var reg 1 , i1 $end
$var reg 1 - i2 $end
$var reg 1 . i3 $end
$var reg 1 / i4 $end
$var reg 1 0 o0 $end
$var reg 1 1 o1 $end
$var reg 1 2 nand260_o0 $end
$var reg 1 3 nand280_o0 $end
$var reg 1 4 nand2100_o0 $end
$var reg 1 5 nand2120_o0 $end
$var reg 1 6 nand2140_o0 $end
$var reg 1 7 nand2160_o0 $end
$upscope $end
$upscope $end
$enddefinitions $end
#0
1!
1"
b00000 #
bUU $
U%
U&
U'
U(
1)
1*
0+
0,
0-
0.
0/
U0
U1
U2
U3
U4
U5
U6
U7
#2000
12
13
14
16
#3000
0!
0"
#4000
b00 $
0%
0'
00
01
05
07
#6000
1!
1"
b10000 #
0&
0(
1/
#8000
06
#9000
0!
0"
#10000
b10 $
1'
11
17
#12000
1!
1"
b00000 #
1(
0/
#14000
16
#15000
0!
0"
#16000
b00 $
0'
01
07
#18000
1!
1"
b01000 #
0(
1.
#20000
#21000
0!
0"
#24000
1!
1"
b00000 #
0.
#26000
#27000
0!
0"
#30000
1!
1"
b11000 #
1.
1/
#32000
06
#33000
0!
0"
#34000
b10 $
1'
11
17
#36000
1!
1"
b00000 #
1(
0.
0/
#38000
16
#39000
0!
0"
#40000
b00 $
0'
01
07
#42000
1!
1"
b00100 #
0(
1-
#44000
#45000
0!
0"
#48000
1!
1"
b00000 #
0-
#50000
#51000
0!
0"
#54000
1!
1"
b10100 #
1-
1/
#56000
06
#57000
0!
0"
#58000
b10 $
1'
11
17
#60000
1!
1"
b00000 #
1(
0-
0/
#62000
16
#63000
0!
0"
#64000
b00 $
0'
01
07
#66000
1!
1"
b01100 #
0(
1-
1.
#68000
03
#69000
0!
0"
#70000
#72000
1!
1"
b00000 #
0-
0.
#74000
13
#75000
0!
0"
#76000
#78000
1!
1"
b11100 #
1-
1.
1/
#80000
03
06
#81000
0!
0"
#82000
b10 $
1'
11
16
17
#84000
1!
1"
b00000 #
b00 $
0'
1(
0-
0.
0/
01
07
#86000
13
#87000
0!
0"
#88000
#90000
1!
1"
b00010 #
0(
1,
#92000
04
#93000
0!
0"
#94000
b11 $
1%
1'
10
11
15
17
#96000
1!
1"
b00000 #
1&
1(
0,
#98000
14
#99000
0!
0"
#100000
b00 $
0%
0'
00
01
05
07
#102000
1!
1"
b10010 #
0&
0(
1,
1/
#104000
04
06
#105000
0!
0"
#106000
b11 $
1%
1'
10
11
15
17
#108000
1!
1"
b00000 #
1&
1(
0,
0/
#110000
14
16
#111000
0!
0"
#112000
b00 $
0%
0'
00
01
05
07
#114000
1!
1"
b01010 #
0&
0(
1,
1.
#116000
04
#117000
0!
0"
#118000
b11 $
1%
1'
10
11
15
17
#120000
1!
1"
b00000 #
1&
1(
0,
0.
#122000
14
#123000
0!
0"
#124000
b00 $
0%
0'
00
01
05
07
#126000
1!
1"
b11010 #
0&
0(
1,
1.
1/
#128000
04
06
#129000
0!
0"
#130000
b11 $
1%
1'
10
11
15
17
#132000
1!
1"
b00000 #
1&
1(
0,
0.
0/
#134000
14
16
#135000
0!
0"
#136000
b00 $
0%
0'
00
01
05
07
#138000
1!
1"
b00110 #
0&
0(
1,
1-
#140000
04
#141000
0!
0"
#142000
b11 $
1%
1'
10
11
15
17
#144000
1!
1"
b00000 #
1&
1(
0,
0-
#146000
14
#147000
0!
0"
#148000
b00 $
0%
0'
00
01
05
07
#150000
1!
1"
b10110 #
0&
0(
1,
1-
1/
#152000
04
06
#153000
0!
0"
#154000
b11 $
1%
1'
10
11
15
17
#156000
1!
1"
b00000 #
1&
1(
0,
0-
0/
#158000
14
16
#159000
0!
0"
#160000
b00 $
0%
0'
00
01
05
07
#162000
1!
1"
b01110 #
0&
0(
1,
1-
1.
#164000
03
04
#165000
0!
0"
#166000
b11 $
1%
1'
10
11
14
15
17
#168000
1!
1"
b00000 #
b00 $
0%
1&
0'
1(
0,
0-
0.
00
01
05
07
#170000
13
#171000
0!
0"
#172000
#174000
1!
1"
b11110 #
0&
0(
1,
1-
1.
1/
#176000
03
04
06
#177000
0!
0"
#178000
b11 $
1%
1'
10
11
14
15
16
17
#180000
1!
1"
b00000 #
b00 $
0%
1&
0'
1(
0,
0-
0.
0/
00
01
05
07
#182000
13
#183000
0!
0"
#184000
#186000
1!
1"
b00001 #
0&
0(
1+
#188000
#189000
0!
0"
#192000
1!
1"
b00000 #
0+
#194000
#195000
0!
0"
#198000
1!
1"
b10001 #
1+
1/
#200000
06
#201000
0!
0"
#202000
b10 $
1'
11
17
#204000
1!
1"
b00000 #
1(
0+
0/
#206000
16
#207000
0!
0"
#208000
b00 $
0'
01
07
#210000
1!
1"
b01001 #
0(
1+
1.
#212000
#213000
0!
0"
#216000
1!
1"
b00000 #
0+
0.
#218000
#219000
0!
0"
#222000
1!
1"
b11001 #
1+
1.
1/
#224000
06
#225000
0!
0"
#226000
b10 $
1'
11
17
#228000
1!
1"
b00000 #
1(
0+
0.
0/
#230000
16
#231000
0!
0"
#232000
b00 $
0'
01
07
#234000
1!
1"
b00101 #
0(
1+
1-
#236000
02
#237000
0!
0"
#238000
b01 $
1%
10
15
#240000
1!
1"
b00000 #
1&
0+
0-
#242000
12
#243000
0!
0"
#244000
b00 $
0%
00
05
#246000
1!
1"
b10101 #
0&
1+
1-
1/
#248000
02
06
#249000
0!
0"
#250000
b11 $
1%
1'
10
11
15
17
#252000
1!
1"
b00000 #
1&
1(
0+
0-
0/
#254000
12
16
#255000
0!
0"
#256000
b00 $
0%
0'
00
01
05
07
#258000
1!
1"
b01101 #
0&
0(
1+
1-
1.
#260000
02
03
#261000
0!
0"
#262000
b01 $
1%
10
15
#264000
1!
1"
b00000 #
1&
0+
0-
0.
#266000
12
13
#267000
0!
0"
#268000
b00 $
0%
00
05
#270000
1!
1"
b11101 #
0&
1+
1-
1.
1/
#272000
02
03
06
#273000
0!
0"
#274000
b11 $
1%
1'
10
11
15
16
17
#276000
1!
1"
b00000 #
b01 $
1&
0'
1(
0+
0-
0.
0/
01
07
#278000
12
13
#279000
0!
0"
#280000
b00 $
0%
00
05
#282000
1!
1"
b00011 #
0&
0(
1+
1,
#284000
04
#285000
0!
0"
#286000
b11 $
1%
1'
10
11
15
17
#288000
1!
1"
b00000 #
1&
1(
0+
0,
#290000
14
#291000
0!
0"
#292000
b00 $
0%
0'
00
01
05
07
#294000
1!
1"
b10011 #
0&
0(
1+
1,
1/
#296000
04
06
#297000
0!
0"
#298000
b11 $
1%
1'
10
11
15
17
#300000
1!
1"
b00000 #
1&
1(
0+
0,
0/
#302000
14
16
#303000
0!
0"
#304000
b00 $
0%
0'
00
01
05
07
#306000
1!
1"
b01011 #
0&
0(
1+
1,
1.
#308000
04
#309000
0!
0"
#310000
b11 $
1%
1'
10
11
15
17
#312000
1!
1"
b00000 #
1&
1(
0+
0,
0.
#314000
14
#315000
0!
0"
#316000
b00 $
0%
0'
00
01
05
07
#318000
1!
1"
b11011 #
0&
0(
1+
1,
1.
1/
#320000
04
06
#321000
0!
0"
#322000
b11 $
1%
1'
10
11
15
17
#324000
1!
1"
b00000 #
1&
1(
0+
0,
0.
0/
#326000
14
16
#327000
0!
0"
#328000
b00 $
0%
0'
00
01
05
07
#330000
1!
1"
b00111 #
0&
0(
1+
1,
1-
#332000
02
04
#333000
0!
0"
#334000
b11 $
1%
1'
10
11
15
17
#336000
1!
1"
b00000 #
1&
1(
0+
0,
0-
#338000
12
14
#339000
0!
0"
#340000
b00 $
0%
0'
00
01
05
07
#342000
1!
1"
b10111 #
0&
0(
1+
1,
1-
1/
#344000
02
04
06
#345000
0!
0"
#346000
b11 $
1%
1'
10
11
15
17
#348000
1!
1"
b00000 #
1&
1(
0+
0,
0-
0/
#350000
12
14
16
#351000
0!
0"
#352000
b00 $
0%
0'
00
01
05
07
#354000
1!
1"
b01111 #
0&
0(
1+
1,
1-
1.
#356000
02
03
04
#357000
0!
0"
#358000
b11 $
1%
1'
10
11
14
15
17
#360000
1!
1"
b00000 #
b01 $
1&
0'
1(
0+
0,
0-
0.
01
07
#362000
12
13
#363000
0!
0"
#364000
b00 $
0%
00
05
#366000
1!
1"
b11111 #
0&
0(
1+
1,
1-
1.
1/
#368000
02
03
04
06
#369000
0!
0"
#370000
b11 $
1%
1'
10
11
14
15
16
17
#372000
1!
1"
b10000 #
b01 $
1&
0'
1(
0+
0,
0-
0.
01
07
#374000
12
13
#375000
0!
0"
#376000
b00 $
0%
00
05
06
#378000
1!
1"
b01000 #
b10 $
0&
1'
0(
1.
0/
11
17
#380000
16
#381000
0!
0"
#382000
b00 $
0'
01
07
#384000
1!
1"
b10000 #
0.
1/
#386000
06
#387000
0!
0"
#388000
b10 $
1'
11
17
#390000
1!
1"
b11000 #
1(
1.
#392000
#393000
0!
0"
#396000
1!
1"
b10000 #
0.
#398000
#399000
0!
0"
#402000
1!
1"
b00100 #
1-
0/
#404000
16
#405000
0!
0"
#406000
b00 $
0'
01
07
#408000
1!
1"
b10000 #
0(
0-
1/
#410000
06
#411000
0!
0"
#412000
b10 $
1'
11
17
#414000
1!
1"
b10100 #
1(
1-
#416000
#417000
0!
0"
#420000
1!
1"
b10000 #
0-
#422000
#423000
0!
0"
#426000
1!
1"
b01100 #
1-
1.
0/
#428000
03
16
#429000
0!
0"
#430000
b00 $
0'
01
07
#432000
1!
1"
b10000 #
0(
0-
0.
1/
#434000
13
#435000
0!
0"
#436000
06
#438000
1!
1"
b11100 #
b10 $
1'
1-
1.
11
17
#440000
03
#441000
0!
0"
#442000
16
#444000
1!
1"
b10000 #
b00 $
0'
1(
0-
0.
01
07
#446000
13
#447000
0!
0"
#448000
06
#450000
1!
1"
b00010 #
b10 $
1'
0(
1,
0/
11
17
#452000
04
16
#453000
0!
0"
#454000
b11 $
1%
10
15
#456000
1!
1"
b10000 #
1&
1(
0,
1/
#458000
14
06
#459000
0!
0"
#460000
b10 $
0%
00
05
#462000
1!
1"
b10010 #
0&
1,
#464000
04
#465000
0!
0"
#466000
b11 $
1%
10
15
#468000
1!
1"
b10000 #
1&
0,
#470000
14
#471000
0!
0"
#472000
b10 $
0%
00
05
#474000
1!
1"
b01010 #
0&
1,
1.
0/
#476000
04
16
#477000
0!
0"
#478000
b11 $
1%
10
15
#480000
1!
1"
b10000 #
1&
0,
0.
1/
#482000
14
06
#483000
0!
0"
#484000
b10 $
0%
00
05
#486000
1!
1"
b11010 #
0&
1,
1.
#488000
04
#489000
0!
0"
#490000
b11 $
1%
10
15
#492000
1!
1"
b10000 #
1&
0,
0.
#494000
14
#495000
0!
0"
#496000
b10 $
0%
00
05
#498000
1!
1"
b00110 #
0&
1,
1-
0/
#500000
04
16
#501000
0!
0"
#502000
b11 $
1%
10
15
#504000
1!
1"
b10000 #
1&
0,
0-
1/
#506000
14
06
#507000
0!
0"
#508000
b10 $
0%
00
05
#510000
1!
1"
b10110 #
0&
1,
1-
#512000
04
#513000
0!
0"
#514000
b11 $
1%
10
15
#516000
1!
1"
b10000 #
1&
0,
0-
#518000
14
#519000
0!
0"
#520000
b10 $
0%
00
05
#522000
1!
1"
b01110 #
0&
1,
1-
1.
0/
#524000
03
04
16
#525000
0!
0"
#526000
b11 $
1%
10
14
15
#528000
1!
1"
b10000 #
b00 $
0%
1&
0'
0,
0-
0.
1/
00
01
05
07
#530000
13
#531000
0!
0"
#532000
06
#534000
1!
1"
b11110 #
b10 $
0&
1'
0(
1,
1-
1.
11
17
#536000
03
04
#537000
0!
0"
#538000
b11 $
1%
10
14
15
16
#540000
1!
1"
b10000 #
b00 $
0%
1&
0'
1(
0,
0-
0.
00
01
05
07
#542000
13
#543000
0!
0"
#544000
06
#546000
1!
1"
b00001 #
b10 $
0&
1'
0(
1+
0/
11
17
#548000
16
#549000
0!
0"
#550000
b00 $
0'
01
07
#552000
1!
1"
b10000 #
0+
1/
#554000
06
#555000
0!
0"
#556000
b10 $
1'
11
17
#558000
1!
1"
b10001 #
1(
1+
#560000
#561000
0!
0"
#564000
1!
1"
b10000 #
0+
#566000
#567000
0!
0"
#570000
1!
1"
b01001 #
1+
1.
0/
#572000
16
#573000
0!
0"
#574000
b00 $
0'
01
07
#576000
1!
1"
b10000 #
0(
0+
0.
1/
#578000
06
#579000
0!
0"
#580000
b10 $
1'
11
17
#582000
1!
1"
b11001 #
1(
1+
1.
#584000
#585000
0!
0"
#588000
1!
1"
b10000 #
0+
0.
#590000
#591000
0!
0"
#594000
1!
1"
b00101 #
1+
1-
0/
#596000
02
16
#597000
0!
0"
#598000
b01 $
1%
0'
10
01
15
07
#600000
1!
1"
b10000 #
1&
0(
0+
0-
1/
#602000
12
06
#603000
0!
0"
#604000
b10 $
0%
1'
00
11
05
17
#606000
1!
1"
b10101 #
0&
1(
1+
1-
#608000
02
#609000
0!
0"
#610000
b11 $
1%
10
15
#612000
1!
1"
b10000 #
1&
0+
0-
#614000
12
#615000
0!
0"
#616000
b10 $
0%
00
05
#618000
1!
1"
b01101 #
0&
1+
1-
1.
0/
#620000
02
03
16
#621000
0!
0"
#622000
b01 $
1%
0'
10
01
15
07
#624000
1!
1"
b10000 #
1&
0(
0+
0-
0.
1/
#626000
12
13
#627000
0!
0"
#628000
b00 $
0%
00
05
06
#630000
1!
1"
b11101 #
b10 $
0&
1'
1+
1-
1.
11
17
#632000
02
03
#633000
0!
0"
#634000
b11 $
1%
10
15
16
#636000
1!
1"
b10000 #
b01 $
1&
0'
1(
0+
0-
0.
01
07
#638000
12
13
#639000
0!
0"
#640000
b00 $
0%
00
05
06
#642000
1!
1"
b00011 #
b10 $
0&
1'
0(
1+
1,
0/
11
17
#644000
04
16
#645000
0!
0"
#646000
b11 $
1%
10
15
#648000
1!
1"
b10000 #
1&
1(
0+
0,
1/
#650000
14
06
#651000
0!
0"
#652000
b10 $
0%
00
05
#654000
1!
1"
b10011 #
0&
1+
1,
#656000
04
#657000
0!
0"
#658000
b11 $
1%
10
15
#660000
1!
1"
b10000 #
1&
0+
0,
#662000
14
#663000
0!
0"
#664000
b10 $
0%
00
05
#666000
1!
1"
b01011 #
0&
1+
1,
1.
0/
#668000
04
16
#669000
0!
0"
#670000
b11 $
1%
10
15
#672000
1!
1"
b10000 #
1&
0+
0,
0.
1/
#674000
14
06
#675000
0!
0"
#676000
b10 $
0%
00
05
#678000
1!
1"
b11011 #
0&
1+
1,
1.
#680000
04
#681000
0!
0"
#682000
b11 $
1%
10
15
#684000
1!
1"
b10000 #
1&
0+
0,
0.
#686000
14
#687000
0!
0"
#688000
b10 $
0%
00
05
#690000
1!
1"
b00111 #
0&
1+
1,
1-
0/
#692000
02
04
16
#693000
0!
0"
#694000
b11 $
1%
10
15
#696000
1!
1"
b10000 #
1&
0+
0,
0-
1/
#698000
12
14
06
#699000
0!
0"
#700000
b10 $
0%
00
05
#702000
1!
1"
b10111 #
0&
1+
1,
1-
#704000
02
04
#705000
0!
0"
#706000
b11 $
1%
10
15
#708000
1!
1"
b10000 #
1&
0+
0,
0-
#710000
12
14
#711000
0!
0"
#712000
b10 $
0%
00
05
#714000
1!
1"
b01111 #
0&
1+
1,
1-
1.
0/
#716000
02
03
04
16
#717000
0!
0"
#718000
b11 $
1%
10
14
15
#720000
1!
1"
b10000 #
b01 $
1&
0'
0+
0,
0-
0.
1/
01
07
#722000
12
13
#723000
0!
0"
#724000
b00 $
0%
00
05
06
#726000
1!
1"
b11111 #
b10 $
0&
1'
0(
1+
1,
1-
1.
11
17
#728000
02
03
04
#729000
0!
0"
#730000
b11 $
1%
10
14
15
16
#732000
1!
1"
b01000 #
b01 $
1&
0'
1(
0+
0,
0-
0/
01
07
#734000
12
13
#735000
0!
0"
#736000
b00 $
0%
00
05
#738000
1!
1"
b11000 #
0&
0(
1/
#740000
06
#741000
0!
0"
#742000
b10 $
1'
11
17
#744000
1!
1"
b01000 #
1(
0/
#746000
16
#747000
0!
0"
#748000
b00 $
0'
01
07
#750000
1!
1"
b00100 #
0(
1-
0.
#752000
#753000
0!
0"
#756000
1!
1"
b01000 #
0-
1.
#758000
#759000
0!
0"
#762000
1!
1"
b10100 #
1-
0.
1/
#764000
06
#765000
0!
0"
#766000
b10 $
1'
11
17
#768000
1!
1"
b01000 #
1(
0-
1.
0/
#770000
16
#771000
0!
0"
#772000
b00 $
0'
01
07
#774000
1!
1"
b01100 #
0(
1-
#776000
03
#777000
0!
0"
#778000
#780000
1!
1"
b01000 #
0-
#782000
13
#783000
0!
0"
#784000
#786000
1!
1"
b11100 #
1-
1/
#788000
03
06
#789000
0!
0"
#790000
b10 $
1'
11
16
17
#792000
1!
1"
b01000 #
b00 $
0'
1(
0-
0/
01
07
#794000
13
#795000
0!
0"
#796000
#798000
1!
1"
b00010 #
0(
1,
0.
#800000
04
#801000
0!
0"
#802000
b11 $
1%
1'
10
11
15
17
#804000
1!
1"
b01000 #
1&
1(
0,
1.
#806000
14
#807000
0!
0"
#808000
b00 $
0%
0'
00
01
05
07
#810000
1!
1"
b10010 #
0&
0(
1,
0.
1/
#812000
04
06
#813000
0!
0"
#814000
b11 $
1%
1'
10
11
15
17
#816000
1!
1"
b01000 #
1&
1(
0,
1.
0/
#818000
14
16
#819000
0!
0"
#820000
b00 $
0%
0'
00
01
05
07
#822000
1!
1"
b01010 #
0&
0(
1,
#824000
04
#825000
0!
0"
#826000
b11 $
1%
1'
10
11
15
17
#828000
1!
1"
b01000 #
1&
1(
0,
#830000
14
#831000
0!
0"
#832000
b00 $
0%
0'
00
01
05
07
#834000
1!
1"
b11010 #
0&
0(
1,
1/
#836000
04
06
#837000
0!
0"
#838000
b11 $
1%
1'
10
11
15
17
#840000
1!
1"
b01000 #
1&
1(
0,
0/
#842000
14
16
#843000
0!
0"
#844000
b00 $
0%
0'
00
01
05
07
#846000
1!
1"
b00110 #
0&
0(
1,
1-
0.
#848000
04
#849000
0!
0"
#850000
b11 $
1%
1'
10
11
15
17
#852000
1!
1"
b01000 #
1&
1(
0,
0-
1.
#854000
14
#855000
0!
0"
#856000
b00 $
0%
0'
00
01
05
07
#858000
1!
1"
b10110 #
0&
0(
1,
1-
0.
1/
#860000
04
06
#861000
0!
0"
#862000
b11 $
1%
1'
10
11
15
17
#864000
1!
1"
b01000 #
1&
1(
0,
0-
1.
0/
#866000
14
16
#867000
0!
0"
#868000
b00 $
0%
0'
00
01
05
07
#870000
1!
1"
b01110 #
0&
0(
1,
1-
#872000
03
04
#873000
0!
0"
#874000
b11 $
1%
1'
10
11
14
15
17
#876000
1!
1"
b01000 #
b00 $
0%
1&
0'
1(
0,
0-
00
01
05
07
#878000
13
#879000
0!
0"
#880000
#882000
1!
1"
b11110 #
0&
0(
1,
1-
1/
#884000
03
04
06
#885000
0!
0"
#886000
b11 $
1%
1'
10
11
14
15
16
17
#888000
1!
1"
b01000 #
b00 $
0%
1&
0'
1(
0,
0-
0/
00
01
05
07
#890000
13
#891000
0!
0"
#892000
#894000
1!
1"
b00001 #
0&
0(
1+
0.
#896000
#897000
0!
0"
#900000
1!
1"
b01000 #
0+
1.
#902000
#903000
0!
0"
#906000
1!
1"
b10001 #
1+
0.
1/
#908000
06
#909000
0!
0"
#910000
b10 $
1'
11
17
#912000
1!
1"
b01000 #
1(
0+
1.
0/
#914000
16
#915000
0!
0"
#916000
b00 $
0'
01
07
#918000
1!
1"
b01001 #
0(
1+
#920000
#921000
0!
0"
#924000
1!
1"
b01000 #
0+
#926000
#927000
0!
0"
#930000
1!
1"
b11001 #
1+
1/
#932000
06
#933000
0!
0"
#934000
b10 $
1'
11
17
#936000
1!
1"
b01000 #
1(
0+
0/
#938000
16
#939000
0!
0"
#940000
b00 $
0'
01
07
#942000
1!
1"
b00101 #
0(
1+
1-
0.
#944000
02
#945000
0!
0"
#946000
b01 $
1%
10
15
#948000
1!
1"
b01000 #
1&
0+
0-
1.
#950000
12
#951000
0!
0"
#952000
b00 $
0%
00
05
#954000
1!
1"
b10101 #
0&
1+
1-
0.
1/
#956000
02
06
#957000
0!
0"
#958000
b11 $
1%
1'
10
11
15
17
#960000
1!
1"
b01000 #
1&
1(
0+
0-
1.
0/
#962000
12
16
#963000
0!
0"
#964000
b00 $
0%
0'
00
01
05
07
#966000
1!
1"
b01101 #
0&
0(
1+
1-
#968000
02
03
#969000
0!
0"
#970000
b01 $
1%
10
15
#972000
1!
1"
b01000 #
1&
0+
0-
#974000
12
13
#975000
0!
0"
#976000
b00 $
0%
00
05
#978000
1!
1"
b11101 #
0&
1+
1-
1/
#980000
02
03
06
#981000
0!
0"
#982000
b11 $
1%
1'
10
11
15
16
17
#984000
1!
1"
b01000 #
b01 $
1&
0'
1(
0+
0-
0/
01
07
#986000
12
13
#987000
0!
0"
#988000
b00 $
0%
00
05
#990000
1!
1"
b00011 #
0&
0(
1+
1,
0.
#992000
04
#993000
0!
0"
#994000
b11 $
1%
1'
10
11
15
17
#996000
1!
1"
b01000 #
1&
1(
0+
0,
1.
#998000
14
#999000
0!
0"
#1000000
b00 $
0%
0'
00
01
05
07
#1002000
1!
1"
b10011 #
0&
0(
1+
1,
0.
1/
#1004000
04
06
#1005000
0!
0"
#1006000
b11 $
1%
1'
10
11
15
17
#1008000
1!
1"
b01000 #
1&
1(
0+
0,
1.
0/
#1010000
14
16
#1011000
0!
0"
#1012000
b00 $
0%
0'
00
01
05
07
#1014000
1!
1"
b01011 #
0&
0(
1+
1,
#1016000
04
#1017000
0!
0"
#1018000
b11 $
1%
1'
10
11
15
17
#1020000
1!
1"
b01000 #
1&
1(
0+
0,
#1022000
14
#1023000
0!
0"
#1024000
b00 $
0%
0'
00
01
05
07
#1026000
1!
1"
b11011 #
0&
0(
1+
1,
1/
#1028000
04
06
#1029000
0!
0"
#1030000
b11 $
1%
1'
10
11
15
17
#1032000
1!
1"
b01000 #
1&
1(
0+
0,
0/
#1034000
14
16
#1035000
0!
0"
#1036000
b00 $
0%
0'
00
01
05
07
#1038000
1!
1"
b00111 #
0&
0(
1+
1,
1-
0.
#1040000
02
04
#1041000
0!
0"
#1042000
b11 $
1%
1'
10
11
15
17
#1044000
1!
1"
b01000 #
1&
1(
0+
0,
0-
1.
#1046000
12
14
#1047000
0!
0"
#1048000
b00 $
0%
0'
00
01
05
07
#1050000
1!
1"
b10111 #
0&
0(
1+
1,
1-
0.
1/
#1052000
02
04
06
#1053000
0!
0"
#1054000
b11 $
1%
1'
10
11
15
17
#1056000
1!
1"
b01000 #
1&
1(
0+
0,
0-
1.
0/
#1058000
12
14
16
#1059000
0!
0"
#1060000
b00 $
0%
0'
00
01
05
07
#1062000
1!
1"
b01111 #
0&
0(
1+
1,
1-
#1064000
02
03
04
#1065000
0!
0"
#1066000
b11 $
1%
1'
10
11
14
15
17
#1068000
1!
1"
b01000 #
b01 $
1&
0'
1(
0+
0,
0-
01
07
#1070000
12
13
#1071000
0!
0"
#1072000
b00 $
0%
00
05
#1074000
1!
1"
b11111 #
0&
0(
1+
1,
1-
1/
#1076000
02
03
04
06
#1077000
0!
0"
#1078000
b11 $
1%
1'
10
11
14
15
16
17
#1080000
1!
1"
b11000 #
b01 $
1&
0'
1(
0+
0,
0-
01
07
#1082000
12
13
#1083000
0!
0"
#1084000
b00 $
0%
00
05
06
#1086000
1!
1"
b00100 #
b10 $
0&
1'
0(
1-
0.
0/
11
17
#1088000
16
#1089000
0!
0"
#1090000
b00 $
0'
01
07
#1092000
1!
1"
b11000 #
0-
1.
1/
#1094000
06
#1095000
0!
0"
#1096000
b10 $
1'
11
17
#1098000
1!
1"
b10100 #
1(
1-
0.
#1100000
#1101000
0!
0"
#1104000
1!
1"
b11000 #
0-
1.
#1106000
#1107000
0!
0"
#1110000
1!
1"
b01100 #
1-
0/
#1112000
03
16
#1113000
0!
0"
#1114000
b00 $
0'
01
07
#1116000
1!
1"
b11000 #
0(
0-
1/
#1118000
13
#1119000
0!
0"
#1120000
06
#1122000
1!
1"
b11100 #
b10 $
1'
1-
11
17
#1124000
03
#1125000
0!
0"
#1126000
16
#1128000
1!
1"
b11000 #
b00 $
0'
1(
0-
01
07
#1130000
13
#1131000
0!
0"
#1132000
06
#1134000
1!
1"
b00010 #
b10 $
1'
0(
1,
0.
0/
11
17
#1136000
04
16
#1137000
0!
0"
#1138000
b11 $
1%
10
15
#1140000
1!
1"
b11000 #
1&
1(
0,
1.
1/
#1142000
14
06
#1143000
0!
0"
#1144000
b10 $
0%
00
05
#1146000
1!
1"
b10010 #
0&
1,
0.
#1148000
04
#1149000
0!
0"
#1150000
b11 $
1%
10
15
#1152000
1!
1"
b11000 #
1&
0,
1.
#1154000
14
#1155000
0!
0"
#1156000
b10 $
0%
00
05
#1158000
1!
1"
b01010 #
0&
1,
0/
#1160000
04
16
#1161000
0!
0"
#1162000
b11 $
1%
10
15
