tests/tmp/or2_d.vhd
--generated automatically
library ieee;
use ieee.std_logic_1164.all;
use ieee.numeric_std.all;
 
entity or2_d is
		generic(delay : time := 1 ps);
		port(
				i0 : in  std_logic;
				i1 : in  std_logic;
				o0 : out std_logic
		);
end or2_d;
 
architecture rtl of or2_d is
begin
		o0 <=  i0 or i1 after delay;
end rtl;

tests/tmp/nand2_d.vhd
-- generated automatically

library ieee;
use ieee.std_logic_1164.all;
use ieee.numeric_std.all;

entity nand2_d is
  generic(delay : time := 1000 fs);
  port (
		i0 : in  std_logic;
		i1 : in  std_logic;
		o0 : out  std_logic
  );
end nand2_d;

architecture bhv of nand2_d is
begin
  o0 <= not(i0 and i1) after delay;
end architecture;

tests/tmp/circ_C17_altered.vhd
library ieee;
use ieee.std_logic_1164.all;
use ieee.numeric_std.all;
 
library gtech_lib;
 
entity circ_C17_altered is
	port(
		i0 : in  std_logic;
		i1 : in  std_logic;
		i2 : in  std_logic;
		i3 : in  std_logic;
		i4 : in  std_logic;
		o0 : out std_logic;
		o1 : out std_logic
	);
end circ_C17_altered;
 
architecture netenos of circ_C17_altered is
	signal Nand260_o0 : std_logic;
	signal Nand280_o0 : std_logic;
	signal Nand2100_o0 : std_logic;
	signal Nand2120_o0 : std_logic;
	signal Nand2140_o0 : std_logic;
	signal Nand2160_o0 : std_logic;
	signal Or2420_o0 : std_logic;
begin
	----------------------------------
	-- Components interconnect 
	----------------------------------
	Nand260 : entity gtech_lib.nand2_d
		generic map(1000 fs)
		port map(
			i0 => Or2420_o0,
			i1 => i2,
			o0 => Nand260_o0
		);
		Nand280 : entity gtech_lib.nand2_d
		generic map(1000 fs)
		port map(
			i0 => i2,
			i1 => i3,
			o0 => Nand280_o0
		);
		Nand2100 : entity gtech_lib.nand2_d
		generic map(1000 fs)
		port map(
			i0 => i1,
			i1 => Nand280_o0,
			o0 => Nand2100_o0
		);
		Nand2120 : entity gtech_lib.nand2_d
		generic map(1000 fs)
		port map(
			i0 => Nand260_o0,
			i1 => Nand2100_o0,
			o0 => Nand2120_o0
		);
		Nand2140 : entity gtech_lib.nand2_d
		generic map(1000 fs)
		port map(
			i0 => i4,
			i1 => Nand280_o0,
			o0 => Nand2140_o0
		);
		Nand2160 : entity gtech_lib.nand2_d
		generic map(1000 fs)
		port map(
			i0 => Nand2100_o0,
			i1 => Nand2140_o0,
			o0 => Nand2160_o0
		);
		Or2420 : entity gtech_lib.or2_d
		generic map(1000 fs)
		port map(
			i0 => i0,
			i1 => i2,
			o0 => Or2420_o0
		);
	----------------------------------
	-- Wiring primary ouputs 
	----------------------------------
	o0 <= Nand2120_o0;
	o1 <= Nand2160_o0;
end netenos;

tests/tmp/circ_C17.vhd
library ieee;
use ieee.std_logic_1164.all;
use ieee.numeric_std.all;
 
library gtech_lib;
 
entity circ_C17 is
	port(
		i0 : in  std_logic;
		i1 : in  std_logic;
		i2 : in  std_logic;
		i3 : in  std_logic;
		i4 : in  std_logic;
		o0 : out std_logic;
		o1 : out std_logic
	);
end circ_C17;
 
architecture netenos of circ_C17 is
	signal Nand260_o0 : std_logic;
	signal Nand280_o0 : std_logic;
	signal Nand2100_o0 : std_logic;
	signal Nand2120_o0 : std_logic;
	signal Nand2140_o0 : std_logic;
	signal Nand2160_o0 : std_logic;
begin
	----------------------------------
	-- Components interconnect 
	----------------------------------
	Nand260 : entity gtech_lib.nand2_d
		generic map(1000 fs)
		port map(
			i0 => i0,
			i1 => i2,
			o0 => Nand260_o0
		);
		Nand280 : entity gtech_lib.nand2_d
		generic map(1000 fs)
		port map(
			i0 => i2,
			i1 => i3,
			o0 => Nand280_o0
		);
		Nand2100 : entity gtech_lib.nand2_d
		generic map(1000 fs)
		port map(
			i0 => i1,
			i1 => Nand280_o0,
			o0 => Nand2100_o0
		);
		Nand2120 : entity gtech_lib.nand2_d
		generic map(1000 fs)
		port map(
			i0 => Nand260_o0,
			i1 => Nand2100_o0,
			o0 => Nand2120_o0
		);
		Nand2140 : entity gtech_lib.nand2_d
		generic map(1000 fs)
		port map(
			i0 => i4,
			i1 => Nand280_o0,
			o0 => Nand2140_o0
		);
		Nand2160 : entity gtech_lib.nand2_d
		generic map(1000 fs)
		port map(
			i0 => Nand2100_o0,
			i1 => Nand2140_o0,
			o0 => Nand2160_o0
		);
	----------------------------------
	-- Wiring primary ouputs 
	----------------------------------
	o0 <= Nand2120_o0;
	o1 <= Nand2160_o0;
end netenos;

tests/tmp/circ_C17_10_tb.vhd
library ieee;
use ieee.std_logic_1164.all;
use ieee.numeric_std.all;
-- use ieee.std_logic_textio.all;

library std;
use std.textio.all;

entity circ_C17_10_tb is
end entity circ_C17_10_tb;

architecture netenos of circ_C17_10_tb is

    constant unit_delay : time := 1 ps; -- default already is 1, thus this line is not mandatory
    -- With a 1-unit model, the maximum path length is equivalent to the minimal period for nominal behavior 
    -- Which means minimum period is 4 for a unit_delay value of 1 (default value) 
    constant nom_period : time := (unit_delay * 7.0);
    constant obs_period : time := (unit_delay * 0.7);
    constant phase : time := 0.0 ps;
    signal nom_clk : std_logic := '1';
    signal obs_clk : std_logic := '1';

    signal tb_in : std_logic_vector(4 downto 0);
    
    signal tb_out_init : std_logic_vector(1 downto 0);
    signal tb_out_alt : std_logic_vector(1 downto 0);
    signal tb_out_diff : std_logic_vector(1 downto 0);

    signal tb_o0 : std_logic; 
	signal tb_o0_s : std_logic;
	signal tb_o1 : std_logic; 
	signal tb_o1_s : std_logic;
	

    signal running : boolean := true;
    signal phase_shift : boolean := false;

begin

    ref_unit : entity work.circ_C17(netenos)
    port map (
       tb_in(0), 
       tb_in(1), 
       tb_in(2), 
       tb_in(3), 
       tb_in(4), 
       tb_out_init(0), 
       tb_out_init(1)
    );

    uut : entity work.circ_C17_altered(netenos)
    port map (
       tb_in(0), 
       tb_in(1), 
       tb_in(2), 
       tb_in(3), 
       tb_in(4), 
       tb_out_alt(0), 
       tb_out_alt(1)
    );

    phase_shift <= true after phase;
    nom_clk <= not(nom_clk) after (nom_period/2) when running else nom_clk;
    obs_clk <= not(obs_clk) after (obs_period/2) when running and phase_shift else obs_clk;

    tb_out_diff(0) <= tb_out_init(0) xor tb_out_alt(0);
	tb_out_diff(1) <= tb_out_init(1) xor tb_out_alt(1);
	

    tb_o0 <= tb_out_diff(0);
	tb_o1 <= tb_out_diff(1);
	

    process(obs_clk)
    begin
        if rising_edge(obs_clk) then
            tb_o0_s <= tb_out_diff(0);
			tb_o1_s <= tb_out_diff(1);
			
        else
            tb_o0_s <= tb_o0_s;
			tb_o1_s <= tb_o1_s;
			
        end if;
    end process;

    stim : process
        file stim_file : text open read_mode is "stim.txt";
        variable text_line : line;
        variable stim_val : std_logic_vector(4 downto 0);
        variable text_val : natural;
    begin
        -- report "Starting simulation...";
        
        while not endfile(stim_file) loop   
            
            readline(stim_file, text_line);
        
            -- Skip empty lines and single-line comments
            if text_line.all'length = 0 or text_line.all(1) = '#' then
                next;
            end if;

            read(text_line, text_val);
           
            stim_val :=  std_logic_vector(to_unsigned(text_val, 5));
            --read(text_line, stim_val);

            for k in 0 to 4 loop
                tb_in(k) <= stim_val(k);
            end loop;

            wait until rising_edge(nom_clk);
        
        end loop;

        wait for nom_period;
        running <= false;
        -- report "Stopping simulation";
        wait;
    end process;

end architecture netenos;

tests/tmp/circ_C17_10_tb.vcd
$date
  Thu Oct  3 17:30:34 2024
$end
$version
  GHDL v0
$end
$timescale
  1 fs
$end
$scope module standard $end
$upscope $end
$scope module textio $end
$upscope $end
$scope module std_logic_1164 $end
$upscope $end
$scope module numeric_std $end
$upscope $end
$scope module circ_c17_10_tb $end
$var reg 1 ! nom_clk $end
$var reg 1 " obs_clk $end
$var reg 5 # tb_in[4:0] $end
$var reg 2 $ tb_out_init[1:0] $end
$var reg 2 % tb_out_alt[1:0] $end
$var reg 2 & tb_out_diff[1:0] $end
$var reg 1 ' tb_o0 $end
$var reg 1 ( tb_o0_s $end
$var reg 1 ) tb_o1 $end
$var reg 1 * tb_o1_s $end
$var reg 1 + running $end
$var reg 1 , phase_shift $end
$scope module ref_unit $end
$var reg 1 - i0 $end
$var reg 1 . i1 $end
$var reg 1 / i2 $end
$var reg 1 0 i3 $end
$var reg 1 1 i4 $end
$var reg 1 2 o0 $end
$var reg 1 3 o1 $end
$var reg 1 4 nand260_o0 $end
$var reg 1 5 nand280_o0 $end
$var reg 1 6 nand2100_o0 $end
$var reg 1 7 nand2120_o0 $end
$var reg 1 8 nand2140_o0 $end
$var reg 1 9 nand2160_o0 $end
$scope module nand260 $end
$var reg 1 : i0 $end
$var reg 1 ; i1 $end
$var reg 1 < o0 $end
$upscope $end
$scope module nand280 $end
$var reg 1 = i0 $end
$var reg 1 > i1 $end
$var reg 1 ? o0 $end
$upscope $end
$scope module nand2100 $end
$var reg 1 @ i0 $end
$var reg 1 A i1 $end
$var reg 1 B o0 $end
$upscope $end
$scope module nand2120 $end
$var reg 1 C i0 $end
$var reg 1 D i1 $end
$var reg 1 E o0 $end
$upscope $end
$scope module nand2140 $end
$var reg 1 F i0 $end
$var reg 1 G i1 $end
$var reg 1 H o0 $end
$upscope $end
$scope module nand2160 $end
$var reg 1 I i0 $end
$var reg 1 J i1 $end
$var reg 1 K o0 $end
$upscope $end
$upscope $end
$scope module uut $end
$var reg 1 L i0 $end
$var reg 1 M i1 $end
$var reg 1 N i2 $end
$var reg 1 O i3 $end
$var reg 1 P i4 $end
$var reg 1 Q o0 $end
$var reg 1 R o1 $end
$var reg 1 S nand260_o0 $end
$var reg 1 T nand280_o0 $end
$var reg 1 U nand2100_o0 $end
$var reg 1 V nand2120_o0 $end
$var reg 1 W nand2140_o0 $end
$var reg 1 X nand2160_o0 $end
$var reg 1 Y or2420_o0 $end
$scope module nand260 $end
$var reg 1 Z i0 $end
$var reg 1 [ i1 $end
$var reg 1 \ o0 $end
$upscope $end
$scope module nand280 $end
$var reg 1 ] i0 $end
$var reg 1 ^ i1 $end
$var reg 1 _ o0 $end
$upscope $end
$scope module nand2100 $end
$var reg 1 ` i0 $end
$var reg 1 a i1 $end
$var reg 1 b o0 $end
$upscope $end
$scope module nand2120 $end
$var reg 1 c i0 $end
$var reg 1 d i1 $end
$var reg 1 e o0 $end
$upscope $end
$scope module nand2140 $end
$var reg 1 f i0 $end
$var reg 1 g i1 $end
$var reg 1 h o0 $end
$upscope $end
$scope module nand2160 $end
$var reg 1 i i0 $end
$var reg 1 j i1 $end
$var reg 1 k o0 $end
$upscope $end
$scope module or2420 $end
$var reg 1 l i0 $end
$var reg 1 m i1 $end
$var reg 1 n o0 $end
$upscope $end
$upscope $end
$upscope $end
$enddefinitions $end
#0
1!
1"
b11100 #
bUU $
bUU %
bUU &
U'
U(
U)
U*
1+
1,
0-
0.
1/
10
11
U2
U3
U4
U5
U6
U7
U8
U9
0:
1;
U<
1=
1>
U?
0@
UA
UB
UC
UD
UE
1F
UG
UH
UI
UJ
UK
0L
0M
1N
1O
1P
UQ
UR
US
UT
UU
UV
UW
UX
UY
UZ
1[
U\
1]
1^
U_
0`
Ua
Ub
Uc
Ud
Ue
1f
Ug
Uh
Ui
Uj
Uk
0l
1m
Un
#350
0"
#700
1"
#1000
14
05
16
1<
0?
0A
1B
1C
1D
UE
0G
UH
1I
UK
0T
1U
1Y
1Z
U\
0_
0a
1b
1d
Ue
0g
Uh
1i
Uk
1n
#1050
0"
#1400
1"
#1750
0"
#2000
bU0 $
02
07
18
1B
0E
1H
1J
UK
0S
1W
0\
1b
0c
Ue
1h
1j
Uk
#2100
1"
#2450
0"
#2800
1"
#3000
b00 $
b01 %
b01 &
1'
0)
03
09
0K
1Q
0R
1V
0X
1e
0k
#3150
0"
#3500
0!
1"
1(
0*
#3850
0"
#4200
1"
#4550
0"
#4900
1"
#5250
0"
#5600
1"
#5950
0"
#6300
1"
#6650
0"
#7000
1!
1"
b11101 #
1-
1:
1L
1l
#7350
0"
#7700
1"
#8000
04
0<
0C
1n
#8050
0"
#8400
1"
#8750
0"
#9000
b01 $
b00 &
0'
12
17
1E
#9100
1"
0(
#9450
0"
#9800
1"
#10150
0"
#10500
0!
1"
#10850
0"
#11200
1"
#11550
0"
#11900
1"
#12250
0"
#12600
1"
#12950
0"
#13300
1"
#13650
0"
#14000
1!
1"
b10001 #
0/
00
0;
0=
0>
0N
0O
0[
0]
0^
0m
#14350
0"
#14700
1"
#15000
14
15
1<
1?
1A
1C
1G
1S
1T
1\
1_
1a
1c
1g
1n
#15050
0"
#15400
1"
#15750
0"
#16000
b00 $
b00 %
02
07
08
1B
0E
0H
0J
0Q
0V
0W
1b
0e
0h
0j
#16100
1"
#16450
0"
#16800
1"
#17000
b10 $
b10 %
13
19
1K
1R
1X
1k
#17150
0"
#17500
0!
1"
#17850
0"
#18200
1"
#18550
0"
#18900
1"
#19250
0"
#19600
1"
#19950
0"
#20300
1"
#20650
0"
#21000
1!
1"
b10101 #
1/
1;
1=
1N
1[
1]
1m
#21350
0"
#21700
1"
#22000
04
0<
1?
0C
0S
0\
1_
0c
1n
#22050
0"
#22400
1"
#22750
0"
#23000
b11 $
b11 %
12
17
1E
1Q
1V
1e
#23100
1"
#23450
0"
#23800
1"
#24150
0"
#24500
0!
1"
#24850
0"
#25200
1"
#25550
0"
#25900
1"
#26250
0"
#26600
1"
#26950
0"
#27300
1"
#27650
0"
#28000
1!
1"
b10000 #
0-
0/
0:
0;
0=
0L
0N
0[
0]
0l
0m
#28350
0"
#28700
1"
#29000
14
1<
1?
1C
1S
0Y
0Z
1\
1_
1c
0n
#29050
0"
#29400
1"
#29750
0"
#30000
b10 $
b10 %
02
07
0E
0Q
0V
1\
0e
#30100
1"
#30450
0"
#30800
1"
#31150
0"
#31500
0!
1"
#31850
0"
#32200
1"
#32550
0"
#32900
1"
#33250
0"
#33600
1"
#33950
0"
#34300
1"
#34650
0"
#35000
1!
1"
b10010 #
1.
1@
1M
1`
#35350
0"
#35700
1"
#36000
06
0B
0D
0I
0U
0b
0d
0i
#36050
0"
#36400
1"
#36750
0"
#37000
b11 $
b11 %
12
17
1E
1K
1Q
1V
1e
1k
#37100
1"
#37450
0"
#37800
1"
#38150
0"
#38500
0!
1"
#38850
0"
#39200
1"
#39550
0"
#39900
1"
#40250
0"
#40600
1"
#40950
0"
#41300
1"
#41650
0"
#42000
1!
1"
b10001 #
1-
0.
1:
0@
1L
0M
0`
1l
#42350
0"
#42700
1"
#43000
16
1<
1B
1D
1I
1U
1Y
1Z
1b
1d
1i
1n
#43050
0"
#43400
1"
#43750
0"
#44000
b10 $
b10 %
02
07
0E
1K
0Q
0V
1\
0e
1k
#44100
1"
#44450
0"
#44800
1"
#45150
0"
#45500
0!
1"
#45850
0"
#46200
1"
#46550
0"
#46900
1"
#47250
0"
#47600
1"
#47950
0"
#48300
1"
#48650
0"
#49000
1!
1"
b10101 #
1/
1;
1=
1N
1[
1]
1m
#49350
0"
#49700
1"
#50000
04
0<
1?
0C
0S
0\
1_
0c
1n
#50050
0"
#50400
1"
#50750
0"
#51000
b11 $
b11 %
12
17
1E
1Q
1V
1e
#51100
1"
#51450
0"
#51800
1"
#52150
0"
#52500
0!
1"
#52850
0"
#53200
1"
#53550
0"
#53900
1"
#54250
0"
#54600
1"
#54950
0"
#55300
1"
#55650
0"
#56000
1!
1"
b00001 #
0/
01
0;
0=
0F
0N
0P
0[
0]
0f
0m
#56350
0"
#56700
1"
#57000
14
18
1<
1?
1C
1H
1J
1S
1W
1\
1_
1c
1h
1j
1n
#57050
0"
#57400
1"
#57750
0"
#58000
b00 $
b00 %
02
03
07
09
0E
0K
0Q
0R
0V
0X
0e
0k
#58100
1"
#58450
0"
#58800
1"
#59150
0"
#59500
0!
1"
#59850
0"
#60200
1"
#60550
0"
#60900
1"
#61250
0"
#61600
1"
#61950
0"
#62300
1"
#62650
0"
#63000
1!
1"
b10001 #
11
1F
1P
1f
#63350
0"
#63700
1"
#64000
08
0H
0J
0W
0h
0j
#64050
0"
#64400
1"
#64750
0"
#65000
b10 $
b10 %
13
19
1K
1R
1X
1k
#65100
1"
#65450
0"
#65800
1"
#66150
0"
#66500
0!
1"
#66850
0"
#67200
1"
#67550
0"
#67900
1"
#68250
0"
#68600
1"
#68950
0"
#69300
1"
#69650
0"
#70000
1!
1"
b11100 #
0-
1/
10
0:
1;
1=
1>
0L
1N
1O
1[
1]
1^
0l
1m
#70350
0"
#70700
1"
#71000
05
1<
0?
0A
0G
0S
0T
0\
0_
0a
0c
0g
1n
#71050
0"
#71400
1"
#71750
0"
#72000
b11 %
b01 &
1'
18
1B
1H
1J
1Q
1V
1W
1b
1e
1h
1j
#72100
1"
1(
#72450
0"
#72800
1"
#73000
b00 $
b01 %
03
09
0K
0R
0X
0k
#73150
0"
#73500
0!
1"
#73850
0"
#74200
1"
#74550
0"
#74900
1"
#75250
0"
#75600
1"
#75950
0"
#76300
1"
#76650
0"
#77000
1!
1"
b11101 #
1-
1:
1L
1l
#77350
0"
#77700
1"
#78000
04
0<
0C
1n
#78050
0"
#78400
1"
#78750
0"
#79000
b01 $
b00 &
0'
12
17
1E
#79100
1"
0(
#79450
0"
#79800
1"
#80150
0"
#80500
0!
1"
#80850
0"
#81200
1"
#81550
0"
#81900
1"
#82250
0"
#82600
1"
#82950
0"
#83300
1"
#83650
0"
#84000
1!
1"
b10000 #
0-
0/
00
0:
0;
0=
0>
0L
0N
0O
0[
0]
0^
0l
0m
#84350
0"
#84700
1"
#85000
14
15
1<
1?
1A
1C
1G
1S
1T
0Y
0Z
1\
1_
1a
1c
1g
0n
#85050
0"
#85400
1"
#85750
0"
#86000
b00 $
b00 %
02
07
08
1B
0E
0H
0J
0Q
0V
0W
1\
1b
0e
0h
0j
#86100
1"
#86450
0"
#86800
1"
#87000
b10 $
b10 %
13
19
1K
1R
1X
1k
#87150
0"
#87500
0!
1"
#87850
0"
#88200
1"
#88550
0"
#88900
1"
#89250
0"
#89600
1"
#89950
0"
#90300
1"
#90650
0"
#91000
1!
1"
b10010 #
1.
1@
1M
1`
#91350
0"
#91700
1"
#92000
06
0B
0D
0I
0U
0b
0d
0i
#92050
0"
#92400
1"
#92750
0"
#93000
b11 $
b11 %
12
17
1E
1K
1Q
1V
1e
1k
#93100
1"
#93450
0"
#93800
1"
#94150
0"
#94500
0!
1"
#94850
0"
#95200
1"
#95550
0"
#95900
1"
#96250
0"
#96600
1"
#96950
0"
#97300
1"
#97650
0"
#98000
1!
1"
b00001 #
1-
0.
01
1:
0@
0F
1L
0M
0P
0`
0f
1l
#98350
0"
#98700
1"
#99000
16
18
1<
1B
1D
1H
1I
1J
1U
1W
1Y
1Z
1b
1d
1h
1i
1j
1n
#99050
0"
#99400
1"
#99750
0"
#100000
b00 $
b00 %
02
03
07
09
0E
0K
0Q
0R
0V
0X
1\
0e
0k
#100100
1"
#100450
0"
#100800
1"
#101150
0"
#101500
0!
1"
#101850
0"
#102200
1"
#102550
0"
#102900
1"
#103250
0"
#103600
1"
#103950
0"
#104300
1"
#104650
0"
#105000
1!
1"
b10001 #
11
1F
1P
1f
#105350
0"
#105700
1"
#106000
08
0H
0J
0W
0h
0j
#106050
0"
#106400
1"
#106750
0"
#107000
b10 $
b10 %
13
19
1K
1R
1X
1k
#107100
1"
#107450
0"
#107800
1"
#108150
0"
#108500
0!
1"
#108850
0"
#109200
1"
#109550
0"
#109900
1"
#110250
0"
#110600
1"
#110950
0"
#111300
1"
#111650
0"
#112000
1!
1"
#112350
0"
#112700
1"
#113050
0"
#113400
1"
#113750
0"
#114100
1"
#114450
0"
#114800
1"
#115150
0"
#115500
0!
1"
#115850
0"
#116200
1"
#116550
0"
#116900
1"
#117250
0"
#117600
1"
#117950
0"
#118300
1"
#118650
0"
#119000
1!
1"
0+
