tests/tmp/and2_d.vhd
--generated automatically
library ieee;
use ieee.std_logic_1164.all;
use ieee.numeric_std.all;
 
entity and2_d is
		generic(delay : time := 1 ps);
		port(
				i0 : in  std_logic;
				i1 : in  std_logic;
				o0 : out std_logic
		);
end and2_d;
 
architecture rtl of and2_d is
begin
		o0 <= i0 and i1 after delay;
end rtl;

tests/tmp/not_d.vhd
-- generated automatically

library ieee;
use ieee.std_logic_1164.all;
use ieee.numeric_std.all;

entity not_d is
  generic(delay : time := 1000 fs);
  port (
		i0 : in  std_logic;
		o0 : out  std_logic
  );
end not_d;

architecture bhv of not_d is
begin
  o0 <= not i0 after delay;
end architecture;

tests/tmp/nor2_d.vhd
--generated automatically
library ieee;
use ieee.std_logic_1164.all;
use ieee.numeric_std.all;
 
entity nor2_d is
		generic(delay : time := 1 ps);
		port(
				i0 : in  std_logic;
				i1 : in  std_logic;
				o0 : out std_logic
		);
end nor2_d;
 
architecture rtl of nor2_d is
begin
		o0 <= i0 nor i1 after delay;
end rtl;

tests/tmp/nand2_d.vhd
-- generated automatically

library ieee;
use ieee.std_logic_1164.all;
use ieee.numeric_std.all;

entity nand2_d is
  generic(delay : time := 1000 fs);
  port (
		i0 : in  std_logic;
		i1 : in  std_logic;
		o0 : out  std_logic
  );
end nand2_d;

architecture bhv of nand2_d is
begin
  o0 <= not(i0 and i1) after delay;
end architecture;

tests/tmp/xor2_d.vhd
--generated automatically
library ieee;
use ieee.std_logic_1164.all;
use ieee.numeric_std.all;
 
entity xor2_d is
		generic(delay : time := 1 ps);
		port(
				i0 : in  std_logic;
				i1 : in  std_logic;
				o0 : out std_logic
		);
end xor2_d;
 
architecture rtl of xor2_d is
begin
		o0 <= i0 xor i1 after delay;
end rtl;

tests/tmp/or2_d.vhd
--generated automatically
library ieee;
use ieee.std_logic_1164.all;
use ieee.numeric_std.all;
 
entity or2_d is
		generic(delay : time := 1 ps);
		port(
				i0 : in  std_logic;
				i1 : in  std_logic;
				o0 : out std_logic
		);
end or2_d;
 
architecture rtl of or2_d is
begin
		o0 <=  i0 or i1 after delay;
end rtl;

tests/tmp/rand_60.vhd
library ieee;
use ieee.std_logic_1164.all;
use ieee.numeric_std.all;
 
library gtech_lib;
 
entity rand_60 is
	port(
		i0 : in  std_logic;
		i1 : in  std_logic;
		i2 : in  std_logic;
		i3 : in  std_logic;
		i4 : in  std_logic;
		i5 : in  std_logic;
		o0 : out std_logic;
		o1 : out std_logic;
		o2 : out std_logic;
		o3 : out std_logic
	);
end rand_60;
 
architecture netenos of rand_60 is
	signal Or21880_o0 : std_logic;
	signal Or21900_o0 : std_logic;
	signal Or21920_o0 : std_logic;
	signal Not1940_o0 : std_logic;
	signal Nor21960_o0 : std_logic;
	signal Or21980_o0 : std_logic;
	signal Not2000_o0 : std_logic;
	signal Nor22020_o0 : std_logic;
	signal Xor22040_o0 : std_logic;
	signal Nor22060_o0 : std_logic;
	signal Nand22080_o0 : std_logic;
	signal And22100_o0 : std_logic;
	signal And22120_o0 : std_logic;
	signal Nor22140_o0 : std_logic;
	signal Not2160_o0 : std_logic;
	signal And22180_o0 : std_logic;
begin
	----------------------------------
	-- Components interconnect 
	----------------------------------
	Or21880 : entity gtech_lib.or2_d
		generic map(1500 fs)
		port map(
			i0 => i0,
			i1 => i5,
			o0 => Or21880_o0
		);
		Or21900 : entity gtech_lib.or2_d
		generic map(1500 fs)
		port map(
			i0 => i1,
			i1 => i3,
			o0 => Or21900_o0
		);
		Or21920 : entity gtech_lib.or2_d
		generic map(1500 fs)
		port map(
			i0 => i2,
			i1 => i4,
			o0 => Or21920_o0
		);
		Not1940 : entity gtech_lib.not_d
		generic map(1000 fs)
		port map(
			i0 => i0,
			o0 => Not1940_o0
		);
		Nor21960 : entity gtech_lib.nor2_d
		generic map(2000 fs)
		port map(
			i0 => Or21880_o0,
			i1 => Not1940_o0,
			o0 => Nor21960_o0
		);
		Or21980 : entity gtech_lib.or2_d
		generic map(1500 fs)
		port map(
			i0 => Or21920_o0,
			i1 => Or21900_o0,
			o0 => Or21980_o0
		);
		Not2000 : entity gtech_lib.not_d
		generic map(1000 fs)
		port map(
			i0 => i3,
			o0 => Not2000_o0
		);
		Nor22020 : entity gtech_lib.nor2_d
		generic map(2000 fs)
		port map(
			i0 => i2,
			i1 => i1,
			o0 => Nor22020_o0
		);
		Xor22040 : entity gtech_lib.xor2_d
		generic map(2500 fs)
		port map(
			i0 => Or21980_o0,
			i1 => Nor21960_o0,
			o0 => Xor22040_o0
		);
		Nor22060 : entity gtech_lib.nor2_d
		generic map(2000 fs)
		port map(
			i0 => Nor22020_o0,
			i1 => Not2000_o0,
			o0 => Nor22060_o0
		);
		Nand22080 : entity gtech_lib.nand2_d
		generic map(2000 fs)
		port map(
			i0 => i5,
			i1 => i4,
			o0 => Nand22080_o0
		);
		And22100 : entity gtech_lib.and2_d
		generic map(1500 fs)
		port map(
			i0 => i2,
			i1 => Or21880_o0,
			o0 => And22100_o0
		);
		And22120 : entity gtech_lib.and2_d
		generic map(1500 fs)
		port map(
			i0 => Xor22040_o0,
			i1 => Nand22080_o0,
			o0 => And22120_o0
		);
		Nor22140 : entity gtech_lib.nor2_d
		generic map(2000 fs)
		port map(
			i0 => And22100_o0,
			i1 => Nor22060_o0,
			o0 => Nor22140_o0
		);
		Not2160 : entity gtech_lib.not_d
		generic map(1000 fs)
		port map(
			i0 => Or21920_o0,
			o0 => Not2160_o0
		);
		And22180 : entity gtech_lib.and2_d
		generic map(1500 fs)
		port map(
			i0 => Not1940_o0,
			i1 => Or21980_o0,
			o0 => And22180_o0
		);
	----------------------------------
	-- Wiring primary ouputs 
	----------------------------------
	o0 <= And22120_o0;
	o1 <= Not2160_o0;
	o2 <= Nor22140_o0;
	o3 <= And22180_o0;
end netenos;

tests/tmp/rand_60_1_tb.vhd
library ieee;
use ieee.std_logic_1164.all;
use ieee.numeric_std.all;
-- use ieee.std_logic_textio.all;

library std;
use std.textio.all;


entity rand_60_1_tb is
end entity rand_60_1_tb;

architecture netenos of rand_60_1_tb is

    constant unit_delay : time := 1 ps; -- default already is 1, thus this line is not mandatory
    -- With a 1-unit model, the maximum path length is equivalent to the minimal period for nominal behavior 
    -- Which means minimum period is 4 for a unit_delay value of 1 (default value) 
    constant nom_period : time := (unit_delay * 7.5);
    constant obs_period : time := (unit_delay * 7.5);
    constant phase : time := 0.0 ps;
    signal nom_clk : std_logic := '1';
    signal obs_clk : std_logic := '1';

    signal tb_in : std_logic_vector(5 downto 0);
    signal tb_out : std_logic_vector(3 downto 0);
    signal tb_o0 : std_logic; 
	signal tb_o0_s : std_logic;
	signal tb_o1 : std_logic; 
	signal tb_o1_s : std_logic;
	signal tb_o2 : std_logic; 
	signal tb_o2_s : std_logic;
	signal tb_o3 : std_logic; 
	signal tb_o3_s : std_logic;
	

    signal running : boolean := true;
    signal phase_shift : boolean := false;

begin

    uut : entity work.rand_60(netenos)
    port map (
       tb_in(0), 
       tb_in(1), 
       tb_in(2), 
       tb_in(3), 
       tb_in(4), 
       tb_in(5), 
       tb_out(0), 
       tb_out(1), 
       tb_out(2), 
       tb_out(3)
    );
    
    phase_shift <= true after phase;
    nom_clk <= not(nom_clk) after (nom_period/2) when running else nom_clk;
    obs_clk <= not(obs_clk) after (obs_period/2) when running and phase_shift else obs_clk;
        
    tb_o0 <= tb_out(0);
	tb_o1 <= tb_out(1);
	tb_o2 <= tb_out(2);
	tb_o3 <= tb_out(3);
	

    process(obs_clk)
    begin
        if rising_edge(obs_clk) then
            tb_o0_s <= tb_out(0);
			tb_o1_s <= tb_out(1);
			tb_o2_s <= tb_out(2);
			tb_o3_s <= tb_out(3);
			
        else
            tb_o0_s <= tb_o0_s;
			tb_o1_s <= tb_o1_s;
			tb_o2_s <= tb_o2_s;
			tb_o3_s <= tb_o3_s;
			
        end if;
    end process;

    stim : process
        file text_file : text open read_mode is "stim.txt";
        variable text_line : line;
        variable stim_val : std_logic_vector(5 downto 0);
        variable text_val : natural;
    begin
        -- report "Starting simulation...";
        
        while not endfile(text_file) loop
            
            readline(text_file, text_line);
           
            -- Skip empty lines and single-line comments
            if text_line.all'length = 0 or text_line.all(1) = '#' then
              next;
            end if;
            
            read(text_line, text_val);
            
            stim_val :=  std_logic_vector(to_unsigned(text_val, 6));
            --read(text_line, stim_val);

            for k in 0 to 5 loop
                tb_in(k) <= stim_val(k);
            end loop;

            wait until rising_edge(nom_clk);
        
        end loop;

        wait for nom_period;
        running <= false;
        -- report "Stopping simulation";
        wait;
    end process;

end architecture netenos;

tests/tmp/rand_60_1_tb.vcd
$date
  Sat Sep 28 19:42:29 2024
$end
$version
  GHDL v0
$end
$timescale
  1 fs
$end
$scope module rand_60_1_tb $end
$var reg 1 ! nom_clk $end
$var reg 1 " obs_clk $end
$var reg 6 # tb_in[5:0] $end
$var reg 4 $ tb_out[3:0] $end
$var reg 1 % tb_o0 $end
$var reg 1 & tb_o0_s $end
$var reg 1 ' tb_o1 $end
$var reg 1 ( tb_o1_s $end
$var reg 1 ) tb_o2 $end
$var reg 1 * tb_o2_s $end
$var reg 1 + tb_o3 $end
$var reg 1 , tb_o3_s $end
$var reg 1 - running $end
$var reg 1 . phase_shift $end
$upscope $end
$enddefinitions $end
#0
1!
1"
b000000 #
bUUUU $
U%
U&
U'
U(
U)
U*
U+
U,
1-
1.
#1000
#1500
#2000
#2500
bUU1U $
1'
#3000
#3500
#3750
0!
0"
#4000
#4500
b0U1U $
0+
#5000
b011U $
1)
#5500
#7000
b0110 $
0%
#7500
1!
1"
b100000 #
0&
1(
1*
0,
#9000
#9500
#10500
#11000
#11250
0!
0"
#15000
1!
1"
b000000 #
#16500
#17000
#18000
#18500
#18750
0!
0"
#22500
1!
1"
b010000 #
#24000
#24500
#25000
b0100 $
0'
#25500
#26250
0!
0"
#27000
b1100 $
1+
#28000
#29500
b1101 $
1%
#30000
1!
1"
b000000 #
1&
0(
1,
#31500
#32000
#32500
b1111 $
1'
#33000
#33750
0!
0"
#34500
b0111 $
0+
#35500
#37000
b0110 $
0%
#37500
1!
1"
b110000 #
0&
1(
0,
#39000
#39500
#40000
b0100 $
0'
#40500
#41000
#41250
0!
0"
#42000
b1100 $
1+
#43000
#44500
#45000
1!
1"
b000000 #
0(
1,
#46500
#47000
#47500
b1110 $
1'
#48000
#48500
b1111 $
1%
#48750
0!
0"
#49500
b0111 $
0+
#50500
#52000
b0110 $
0%
#52500
1!
1"
b001000 #
1(
0,
#53500
#54000
#55500
#56250
0!
0"
#57000
b1110 $
1+
#58000
#59500
b1111 $
1%
#60000
1!
1"
b000000 #
1&
1,
#61000
#61500
#63000
#63750
0!
0"
#64500
b0111 $
0+
#65500
#67000
b0110 $
0%
#67500
1!
1"
b101000 #
0&
0,
#68500
#69000
#69500
#70500
#71000
#71250
0!
0"
#72000
b1110 $
1+
#73000
#74500
b1111 $
1%
#75000
1!
1"
b000000 #
1&
1,
#76000
#76500
#77000
#78000
#78500
#78750
0!
0"
#79500
b0111 $
0+
#80500
#82000
b0110 $
0%
#82500
1!
1"
b011000 #
0&
0,
#83500
#84000
#84500
#85000
b0100 $
0'
#85500
#86250
0!
0"
#87000
b1100 $
1+
#88000
#89500
b1101 $
1%
#90000
1!
1"
b000000 #
1&
0(
1,
#91000
#91500
#92000
#92500
b1111 $
1'
#93000
#93750
0!
0"
#94500
b0111 $
0+
#95500
#97000
b0110 $
0%
#97500
1!
1"
b111000 #
0&
1(
0,
#98500
#99000
#99500
#100000
b0100 $
0'
#100500
#101000
#101250
0!
0"
#102000
b1100 $
1+
#103000
#104500
#105000
1!
1"
b000000 #
0(
1,
#106000
#106500
#107000
#107500
b1110 $
1'
#108000
#108500
b1111 $
1%
#108750
0!
0"
#109500
b0111 $
0+
#110500
#112000
b0110 $
0%
#112500
1!
1"
b000100 #
1(
0,
#114000
#114500
#115000
b0100 $
0'
#115500
#116250
0!
0"
#116500
#117000
b1100 $
1+
#118000
#119500
b1101 $
1%
#120000
1!
1"
b000000 #
1&
0(
1,
#121500
#122000
#122500
b1111 $
1'
#123000
#123750
0!
0"
#124000
#124500
b0111 $
0+
#125500
#127000
b0110 $
0%
#127500
1!
1"
b100100 #
0&
1(
0,
#129000
#129500
#130000
b0100 $
0'
#130500
#131000
#131250
0!
0"
#131500
#132000
b1100 $
1+
#132500
b1000 $
0)
#133000
#134500
b1001 $
1%
#135000
1!
1"
b000000 #
1&
0(
0*
1,
#136500
#137000
#137500
b1011 $
1'
#138000
#138500
b1111 $
1)
#138750
0!
0"
#139000
#139500
b0111 $
0+
#140500
#142000
b0110 $
0%
#142500
1!
1"
b010100 #
0&
1(
1*
0,
#144000
#144500
#145000
b0100 $
0'
#145500
#146250
0!
0"
#146500
#147000
b1100 $
1+
#148000
#149500
b1101 $
1%
#150000
1!
1"
b000000 #
1&
0(
1,
#151500
#152000
#152500
b1111 $
1'
#153000
#153750
0!
0"
#154000
#154500
b0111 $
0+
#155500
#157000
b0110 $
0%
#157500
1!
1"
b110100 #
0&
1(
0,
#159000
#159500
#160000
b0100 $
0'
#160500
#161000
#161250
0!
0"
#161500
#162000
b1100 $
1+
#162500
b1000 $
0)
#163000
#164500
#165000
1!
1"
b000000 #
0(
0*
1,
#166500
#167000
#167500
b1010 $
1'
#168000
#168500
b1111 $
1%
1)
#168750
0!
0"
#169000
#169500
b0111 $
0+
#170500
#172000
b0110 $
0%
#172500
1!
1"
b001100 #
1(
1*
0,
#173500
#174000
#174500
#175000
b0100 $
0'
#175500
#176250
0!
0"
#176500
#177000
b1100 $
1+
#178000
#178500
b1000 $
0)
#179500
b1001 $
1%
#180000
1!
1"
b000000 #
1&
0(
0*
1,
#181000
#181500
#182000
#182500
b1011 $
1'
#183000
#183750
0!
0"
#184000
#184500
b0011 $
0+
#185000
b0111 $
1)
#185500
#187000
b0110 $
0%
#187500
1!
1"
b101100 #
0&
1(
1*
0,
#188500
#189000
#189500
#190000
b0100 $
0'
#190500
#191000
#191250
0!
0"
#191500
#192000
b1100 $
1+
#192500
b1000 $
0)
#193000
#193500
#194500
b1001 $
1%
#195000
1!
1"
b000000 #
1&
0(
0*
1,
#196000
#196500
#197000
#197500
b1011 $
1'
#198000
#198500
#198750
0!
0"
#199000
#199500
b0011 $
0+
#200000
b0111 $
1)
#200500
#202000
b0110 $
0%
#202500
1!
1"
b011100 #
0&
1(
1*
0,
#203500
#204000
#204500
#205000
b0100 $
0'
#205500
#206250
0!
0"
#206500
#207000
b1100 $
1+
#208000
#208500
b1000 $
0)
#209500
b1001 $
1%
#210000
1!
1"
b000000 #
1&
0(
0*
1,
#211000
#211500
#212000
#212500
b1011 $
1'
#213000
#213750
0!
0"
#214000
#214500
b0011 $
0+
#215000
b0111 $
1)
#215500
#217000
b0110 $
0%
#217500
1!
1"
b111100 #
0&
1(
1*
0,
#218500
#219000
#219500
#220000
b0100 $
0'
#220500
#221000
#221250
0!
0"
#221500
#222000
b1100 $
1+
#222500
b1000 $
0)
#223000
#223500
#224500
#225000
1!
1"
b000000 #
0(
0*
1,
#226000
#226500
#227000
#227500
b1010 $
1'
#228000
#228500
b1011 $
1%
#228750
0!
0"
#229000
#229500
b0011 $
0+
#230000
b0111 $
1)
#230500
#232000
b0110 $
0%
#232500
1!
1"
b000010 #
1(
1*
0,
#234000
#234500
#235500
#236250
0!
0"
#236500
#237000
b1110 $
1+
#238000
#239500
b1111 $
1%
#240000
1!
1"
b000000 #
1&
1,
#241500
#242000
#243000
#243750
0!
0"
#244000
#244500
b0111 $
0+
#245500
#247000
b0110 $
0%
#247500
1!
1"
b100010 #
0&
0,
#249000
#249500
#250500
#251000
#251250
0!
0"
#251500
#252000
b1110 $
1+
#253000
#254500
b1111 $
1%
#255000
1!
1"
b000000 #
1&
1,
#256500
#257000
#258000
#258500
#258750
0!
0"
#259000
#259500
b0111 $
0+
#260500
#262000
b0110 $
0%
#262500
1!
1"
b010010 #
0&
0,
#264000
#264500
#265000
b0100 $
0'
#265500
#266250
0!
0"
#266500
#267000
b1100 $
1+
#268000
#269500
b1101 $
1%
#270000
1!
1"
b000000 #
1&
0(
1,
#271500
#272000
#272500
b1111 $
1'
#273000
#273750
0!
0"
#274000
#274500
b0111 $
0+
#275500
#277000
b0110 $
0%
#277500
1!
1"
b110010 #
0&
1(
0,
#279000
#279500
#280000
b0100 $
0'
#280500
#281000
#281250
0!
0"
#281500
#282000
b1100 $
1+
#283000
#284500
#285000
1!
1"
b000000 #
0(
1,
#286500
#287000
#287500
b1110 $
1'
#288000
#288500
b1111 $
1%
#288750
0!
0"
#289000
#289500
b0111 $
0+
#290500
#292000
b0110 $
0%
#292500
1!
1"
b001010 #
1(
0,
#293500
#294000
#294500
#295500
#296250
0!
0"
#296500
#297000
b1110 $
1+
#298000
#298500
b1010 $
0)
#299500
b1011 $
1%
#300000
1!
1"
b000000 #
1&
0*
1,
#301000
#301500
#302000
#303000
#303750
0!
0"
#304000
#304500
b0011 $
0+
#305000
b0111 $
1)
#305500
#307000
b0110 $
0%
#307500
1!
1"
b101010 #
0&
1*
0,
#308500
#309000
#309500
#310500
#311000
#311250
0!
0"
#311500
#312000
b1110 $
1+
#313000
#313500
b1010 $
0)
#314500
b1011 $
1%
#315000
1!
1"
b000000 #
1&
0*
1,
#316000
#316500
#317000
#318000
#318500
#318750
0!
0"
#319000
#319500
b0011 $
0+
#320000
b0111 $
1)
#320500
#322000
b0110 $
0%
#322500
1!
1"
b011010 #
0&
1*
0,
#323500
#324000
#324500
#325000
b0100 $
0'
#325500
#326250
0!
0"
#326500
#327000
b1100 $
1+
#328000
#328500
b1000 $
0)
#329500
b1001 $
1%
#330000
1!
1"
b000000 #
1&
0(
0*
1,
#331000
#331500
#332000
#332500
b1011 $
1'
#333000
#333750
0!
0"
#334000
#334500
b0011 $
0+
#335000
b0111 $
1)
#335500
#337000
b0110 $
0%
#337500
1!
1"
b111010 #
0&
1(
1*
0,
#338500
#339000
#339500
#340000
b0100 $
0'
#340500
#341000
#341250
0!
0"
#341500
#342000
b1100 $
1+
#343000
#343500
b1000 $
0)
#344500
#345000
1!
1"
b000000 #
0(
0*
1,
#346000
#346500
#347000
#347500
b1010 $
1'
#348000
#348500
b1011 $
1%
#348750
0!
0"
#349000
#349500
b0011 $
0+
#350000
b0111 $
1)
#350500
#352000
b0110 $
0%
#352500
1!
1"
b000110 #
1(
1*
0,
#354000
#354500
#355000
b0100 $
0'
#355500
#356250
0!
0"
#356500
#357000
b1100 $
1+
#358000
#359500
b1101 $
1%
#360000
1!
1"
b000000 #
1&
0(
1,
#361500
#362000
#362500
b1111 $
1'
#363000
#363750
0!
0"
#364000
#364500
b0111 $
0+
#365500
#367000
b0110 $
0%
#367500
1!
1"
b100110 #
0&
1(
0,
#369000
#369500
#370000
b0100 $
0'
#370500
#371000
#371250
0!
0"
#371500
#372000
b1100 $
1+
#372500
b1000 $
0)
#373000
#374500
b1001 $
1%
#375000
1!
1"
b000000 #
1&
0(
0*
1,
#376500
#377000
#377500
b1011 $
1'
#378000
#378500
b1111 $
1)
#378750
0!
0"
#379000
#379500
b0111 $
0+
#380500
#382000
b0110 $
0%
#382500
1!
1"
b010110 #
0&
1(
1*
0,
#384000
#384500
#385000
b0100 $
0'
#385500
#386250
0!
0"
#386500
#387000
b1100 $
1+
#388000
#389500
b1101 $
1%
#390000
1!
1"
b000000 #
1&
0(
1,
#391500
#392000
#392500
b1111 $
1'
#393000
#393750
0!
0"
#394000
#394500
b0111 $
0+
#395500
#397000
b0110 $
0%
#397500
1!
1"
b110110 #
0&
1(
0,
#399000
#399500
#400000
b0100 $
0'
#400500
#401000
#401250
0!
0"
#401500
#402000
b1100 $
1+
#402500
b1000 $
0)
#403000
#404500
#405000
1!
1"
b000000 #
0(
0*
1,
#406500
#407000
#407500
b1010 $
1'
#408000
#408500
b1111 $
1%
1)
#408750
0!
0"
#409000
#409500
b0111 $
0+
#410500
#412000
b0110 $
0%
#412500
1!
1"
b001110 #
1(
1*
0,
#413500
#414000
#414500
#415000
b0100 $
0'
#415500
#416250
0!
0"
#416500
#417000
b1100 $
1+
#418000
#418500
b1000 $
0)
#419500
b1001 $
1%
#420000
1!
1"
b000000 #
1&
0(
0*
1,
#421000
#421500
#422000
#422500
b1011 $
1'
#423000
#423750
0!
0"
#424000
#424500
b0011 $
0+
#425000
b0111 $
1)
#425500
#427000
b0110 $
0%
#427500
1!
1"
b101110 #
0&
1(
1*
0,
#428500
#429000
#429500
#430000
b0100 $
0'
#430500
#431000
#431250
0!
0"
#431500
#432000
b1100 $
1+
#432500
b1000 $
0)
#433000
#433500
#434500
b1001 $
1%
#435000
1!
1"
b000000 #
1&
0(
0*
1,
#436000
#436500
#437000
#437500
b1011 $
1'
#438000
#438500
#438750
0!
0"
#439000
#439500
b0011 $
0+
#440000
b0111 $
1)
#440500
#442000
b0110 $
0%
#442500
1!
1"
b011110 #
0&
1(
1*
0,
#443500
#444000
#444500
#445000
b0100 $
0'
#445500
#446250
0!
0"
#446500
#447000
b1100 $
1+
#448000
#448500
b1000 $
0)
#449500
b1001 $
1%
#450000
1!
1"
b000000 #
1&
0(
0*
1,
#451000
#451500
#452000
#452500
b1011 $
1'
#453000
#453750
0!
0"
#454000
#454500
b0011 $
0+
#455000
b0111 $
1)
#455500
#457000
b0110 $
0%
#457500
1!
1"
b111110 #
0&
1(
1*
0,
#458500
#459000
#459500
#460000
b0100 $
0'
#460500
#461000
#461250
0!
0"
#461500
#462000
b1100 $
1+
#462500
b1000 $
0)
#463000
#463500
#464500
#465000
1!
1"
b000000 #
0(
0*
1,
#466000
#466500
#467000
#467500
b1010 $
1'
#468000
#468500
b1011 $
1%
#468750
0!
0"
#469000
#469500
b0011 $
0+
#470000
b0111 $
1)
#470500
#472000
b0110 $
0%
#472500
1!
1"
b000001 #
1(
1*
0,
#473500
#474000
#475000
#475500
#476000
#476250
0!
0"
#480000
1!
1"
b000000 #
#481000
#481500
#482500
#483000
#483500
#483750
0!
0"
#487500
1!
1"
b100001 #
#488500
#489000
#489500
#490000
#490500
#491000
#491250
0!
0"
#495000
1!
1"
b000000 #
#496000
#496500
#497000
#497500
#498000
#498500
#498750
0!
0"
#502500
1!
1"
b010001 #
#503500
#504000
#504500
#505000
b0100 $
0'
#505500
#506000
#506250
0!
0"
#507000
#508000
#509500
b0101 $
1%
#510000
1!
1"
b000000 #
1&
0(
#511000
#511500
#512000
#512500
b1111 $
1'
1+
#513000
#513500
#513750
0!
0"
#514500
b0111 $
0+
#515500
#517000
b0110 $
0%
#517500
1!
1"
b110001 #
0&
1(
#518500
#519000
#519500
#520000
b0100 $
0'
#520500
#521000
#521250
0!
0"
#522000
#523000
#524500
#525000
1!
1"
b000000 #
0(
#526000
#526500
#527000
#527500
b1110 $
1'
1+
#528000
#528500
b1111 $
1%
#528750
0!
0"
#529500
b0111 $
0+
#530500
#532000
b0110 $
0%
#532500
1!
1"
b001001 #
1(
#533500
#534000
#535000
#535500
#536000
#536250
0!
0"
#537000
#538000
#539500
b0111 $
1%
#540000
1!
1"
b000000 #
1&
#541000
#541500
#542500
b1111 $
1+
#543000
#543500
#543750
0!
0"
#544500
b0111 $
0+
#545500
#547000
b0110 $
0%
#547500
1!
1"
b101001 #
0&
#548500
#549000
#549500
#550000
#550500
#551000
#551250
0!
0"
#552000
#553000
#554500
b0111 $
1%
#555000
1!
1"
b000000 #
1&
#556000
#556500
#557000
#557500
b1111 $
1+
#558000
#558500
#558750
0!
0"
#559500
b0111 $
0+
#560500
#562000
b0110 $
0%
#562500
1!
1"
b011001 #
0&
#563500
#564000
#564500
#565000
b0100 $
0'
#565500
#566000
#566250
0!
0"
#567000
#568000
#569500
b0101 $
1%
#570000
1!
1"
b000000 #
1&
0(
#571000
#571500
#572000
#572500
b1111 $
1'
1+
#573000
#573500
#573750
0!
0"
#574500
b0111 $
0+
#575500
#577000
b0110 $
0%
#577500
1!
1"
b111001 #
0&
1(
#578500
#579000
#579500
#580000
b0100 $
0'
#580500
#581000
#581250
0!
0"
#582000
#583000
#584500
#585000
1!
1"
b000000 #
0(
#586000
#586500
#587000
#587500
b1110 $
1'
1+
#588000
#588500
b1111 $
1%
#588750
0!
0"
#589500
b0111 $
0+
#590500
#592000
b0110 $
0%
#592500
1!
1"
b000101 #
1(
#593500
#594000
#594500
#595000
b0100 $
0'
#595500
#596000
#596250
0!
0"
#596500
#597000
#597500
b0000 $
0)
#598000
#599500
b0001 $
1%
#600000
1!
1"
b000000 #
1&
0(
0*
#601000
#601500
#602000
#602500
b1011 $
1'
1+
#603000
#603500
b1111 $
1)
#603750
0!
0"
#604000
#604500
b0111 $
0+
#605500
#607000
b0110 $
0%
#607500
1!
1"
b100101 #
0&
1(
1*
#608500
#609000
#609500
#610000
b0100 $
0'
#610500
#611000
#611250
0!
0"
#611500
#612000
#612500
b0000 $
0)
#613000
#614500
b0001 $
1%
#615000
1!
1"
b000000 #
1&
0(
0*
#616000
#616500
#617000
#617500
b1011 $
1'
1+
#618000
#618500
b1111 $
1)
#618750
0!
0"
#619000
#619500
b0111 $
0+
#620500
#622000
b0110 $
0%
#622500
1!
1"
b010101 #
0&
1(
1*
#623500
#624000
#624500
#625000
b0100 $
0'
#625500
#626000
#626250
0!
0"
#626500
#627000
#627500
b0000 $
0)
#628000
#629500
b0001 $
1%
#630000
1!
1"
b000000 #
1&
0(
0*
#631000
#631500
#632000
#632500
b1011 $
1'
1+
#633000
#633500
b1111 $
1)
#633750
0!
0"
#634000
#634500
b0111 $
0+
#635500
#637000
b0110 $
0%
#637500
1!
1"
b110101 #
0&
1(
1*
#638500
#639000
#639500
#640000
b0100 $
0'
#640500
#641000
#641250
0!
0"
#641500
#642000
#642500
b0000 $
0)
#643000
#644500
#645000
1!
1"
b000000 #
0(
0*
#646000
#646500
#647000
#647500
b1010 $
1'
1+
#648000
#648500
b1111 $
1%
1)
#648750
0!
0"
#649000
#649500
b0111 $
0+
#650500
#652000
b0110 $
0%
#652500
1!
1"
b001101 #
1(
1*
#653500
#654000
#654500
#655000
b0100 $
0'
#655500
#656000
#656250
0!
0"
#656500
#657000
#657500
b0000 $
0)
#658000
#658500
#659500
b0001 $
1%
#660000
1!
1"
b000000 #
1&
0(
0*
#661000
#661500
#662000
#662500
b1011 $
1'
1+
#663000
#663500
#663750
0!
0"
#664000
#664500
b0011 $
0+
#665000
b0111 $
1)
#665500
#667000
b0110 $
0%
#667500
1!
1"
b101101 #
0&
1(
1*
#668500
#669000
#669500
#670000
b0100 $
0'
#670500
#671000
#671250
0!
0"
#671500
#672000
#672500
b0000 $
0)
#673000
#673500
#674500
b0001 $
1%
#675000
1!
1"
b000000 #
1&
0(
0*
#676000
#676500
#677000
#677500
b1011 $
1'
1+
#678000
#678500
#678750
0!
0"
#679000
#679500
b0011 $
0+
#680000
b0111 $
1)
#680500
#682000
b0110 $
0%
#682500
1!
1"
b011101 #
0&
1(
1*
#683500
#684000
#684500
#685000
b0100 $
0'
#685500
#686000
#686250
0!
0"
#686500
#687000
#687500
b0000 $
0)
#688000
#688500
#689500
b0001 $
1%
#690000
1!
1"
b000000 #
1&
0(
0*
#691000
#691500
#692000
#692500
b1011 $
1'
1+
#693000
#693500
#693750
0!
0"
#694000
#694500
b0011 $
0+
#695000
b0111 $
1)
#695500
#697000
b0110 $
0%
#697500
1!
1"
b111101 #
0&
1(
1*
#698500
#699000
#699500
#700000
b0100 $
0'
#700500
#701000
#701250
0!
0"
#701500
#702000
#702500
b0000 $
0)
#703000
#703500
#704500
#705000
1!
1"
b000000 #
0(
0*
#706000
#706500
#707000
#707500
b1010 $
1'
1+
#708000
#708500
b1011 $
1%
#708750
0!
0"
#709000
#709500
b0011 $
0+
#710000
b0111 $
1)
#710500
#712000
b0110 $
0%
#712500
1!
1"
b000011 #
1(
1*
#713500
#714000
#714500
#715000
#715500
#716000
#716250
0!
0"
#716500
#717000
#718000
#719500
b0111 $
1%
#720000
1!
1"
b000000 #
1&
#721000
#721500
#722000
#722500
b1111 $
1+
#723000
#723500
#723750
0!
0"
#724000
#724500
b0111 $
0+
#725500
#727000
b0110 $
0%
#727500
1!
1"
b100011 #
0&
#728500
#729000
#729500
#730000
#730500
#731000
#731250
0!
0"
#731500
#732000
#733000
#734500
b0111 $
1%
#735000
1!
1"
b000000 #
1&
#736000
#736500
#737000
#737500
b1111 $
1+
#738000
#738500
#738750
0!
0"
#739000
#739500
b0111 $
0+
#740500
#742000
b0110 $
0%
#742500
1!
1"
b010011 #
0&
#743500
#744000
#744500
#745000
b0100 $
0'
#745500
#746000
#746250
0!
0"
#746500
#747000
#748000
#749500
b0101 $
1%
#750000
1!
1"
b000000 #
1&
0(
#751000
#751500
#752000
#752500
b1111 $
1'
1+
#753000
#753500
#753750
0!
0"
#754000
#754500
b0111 $
0+
#755500
#757000
b0110 $
0%
#757500
1!
1"
b110011 #
0&
1(
#758500
#759000
#759500
#760000
b0100 $
0'
#760500
#761000
#761250
0!
0"
#761500
#762000
#763000
#764500
#765000
1!
1"
b000000 #
0(
#766000
#766500
#767000
#767500
b1110 $
1'
1+
#768000
#768500
b1111 $
1%
#768750
0!
0"
#769000
#769500
b0111 $
0+
#770500
#772000
b0110 $
0%
#772500
1!
1"
b001011 #
1(
#773500
#774000
#774500
#775000
#775500
#776000
#776250
0!
0"
#776500
#777000
#778000
#778500
b0010 $
0)
#779500
b0011 $
1%
#780000
1!
1"
b000000 #
1&
0*
#781000
#781500
#782000
#782500
b1011 $
1+
#783000
#783500
#783750
0!
0"
#784000
#784500
b0011 $
0+
#785000
b0111 $
1)
#785500
#787000
b0110 $
0%
#787500
1!
1"
b101011 #
0&
1*
#788500
#789000
#789500
#790000
#790500
#791000
#791250
0!
0"
#791500
