tests/tmp/and2_d.vhd
--generated automatically
library ieee;
use ieee.std_logic_1164.all;
use ieee.numeric_std.all;
 
entity and2_d is
		generic(delay : time := 1 ps);
		port(
				i0 : in  std_logic;
				i1 : in  std_logic;
				o0 : out std_logic
		);
end and2_d;
 
architecture rtl of and2_d is
begin
		o0 <= i0 and i1 after delay;
end rtl;

tests/tmp/nor2_d.vhd
--generated automatically
library ieee;
use ieee.std_logic_1164.all;
use ieee.numeric_std.all;
 
entity nor2_d is
		generic(delay : time := 1 ps);
		port(
				i0 : in  std_logic;
				i1 : in  std_logic;
				o0 : out std_logic
		);
end nor2_d;
 
architecture rtl of nor2_d is
begin
		o0 <= i0 nor i1 after delay;
end rtl;

tests/tmp/not_d.vhd
-- generated automatically

library ieee;
use ieee.std_logic_1164.all;
use ieee.numeric_std.all;

entity not_d is
  generic(delay : time := 1000 fs);
  port (
		i0 : in  std_logic;
		o0 : out  std_logic
  );
end not_d;

architecture bhv of not_d is
begin
  o0 <= not i0 after delay;
end architecture;

tests/tmp/or2_d.vhd
--generated automatically
library ieee;
use ieee.std_logic_1164.all;
use ieee.numeric_std.all;
 
entity or2_d is
		generic(delay : time := 1 ps);
		port(
				i0 : in  std_logic;
				i1 : in  std_logic;
				o0 : out std_logic
		);
end or2_d;
 
architecture rtl of or2_d is
begin
		o0 <=  i0 or i1 after delay;
end rtl;

tests/tmp/nand2_d.vhd
--generated automatically
library ieee;
use ieee.std_logic_1164.all;
use ieee.numeric_std.all;
 
entity nand2_d is
		generic(delay : time := 1 ps);
		port(
				i0 : in  std_logic;
				i1 : in  std_logic;
				o0 : out std_logic
		);
end nand2_d;
 
architecture rtl of nand2_d is
begin
		o0 <=  i0 nand i1 after delay;
end rtl;

tests/tmp/xor2_d.vhd
--generated automatically
library ieee;
use ieee.std_logic_1164.all;
use ieee.numeric_std.all;
 
entity xor2_d is
		generic(delay : time := 1 ps);
		port(
				i0 : in  std_logic;
				i1 : in  std_logic;
				o0 : out std_logic
		);
end xor2_d;
 
architecture rtl of xor2_d is
begin
		o0 <= i0 xor i1 after delay;
end rtl;

tests/tmp/test.vhd
library ieee;
use ieee.std_logic_1164.all;
use ieee.numeric_std.all;
 
library gtech_lib;
 
entity test is
	port(
		i0 : in  std_logic;
		i1 : in  std_logic;
		i2 : in  std_logic;
		i3 : in  std_logic;
		i4 : in  std_logic;
		i5 : in  std_logic;
		o0 : out std_logic;
		o1 : out std_logic;
		o2 : out std_logic;
		o3 : out std_logic
	);
end test;
 
architecture netenos of test is
	signal Or236260_o0 : std_logic;
	signal Or236280_o0 : std_logic;
	signal Or236300_o0 : std_logic;
	signal Xor236320_o0 : std_logic;
	signal Nor236340_o0 : std_logic;
	signal Xor236360_o0 : std_logic;
	signal And236380_o0 : std_logic;
	signal Nor236400_o0 : std_logic;
	signal Xor236420_o0 : std_logic;
	signal Nor236440_o0 : std_logic;
	signal Xor236460_o0 : std_logic;
	signal Nand236480_o0 : std_logic;
	signal Not36500_o0 : std_logic;
	signal And236520_o0 : std_logic;
	signal Nor236540_o0 : std_logic;
	signal Nor236560_o0 : std_logic;
	signal Nor236580_o0 : std_logic;
	signal Or236600_o0 : std_logic;
	signal Not36620_o0 : std_logic;
	signal Nor236640_o0 : std_logic;
	signal Or236660_o0 : std_logic;
	signal Xor236680_o0 : std_logic;
	signal And236700_o0 : std_logic;
	signal Nor236720_o0 : std_logic;
	signal Nor236740_o0 : std_logic;
	signal Or236760_o0 : std_logic;
	signal Nor236780_o0 : std_logic;
	signal Xor236800_o0 : std_logic;
	signal Or236820_o0 : std_logic;
	signal Nand236840_o0 : std_logic;
	signal And236860_o0 : std_logic;
	signal Nor236880_o0 : std_logic;
	signal Nor236900_o0 : std_logic;
	signal Nor236920_o0 : std_logic;
	signal Nand236940_o0 : std_logic;
	signal Or236960_o0 : std_logic;
	signal Not36980_o0 : std_logic;
	signal Nor237000_o0 : std_logic;
	signal Nor237020_o0 : std_logic;
	signal And237040_o0 : std_logic;
begin
	----------------------------------
	-- Components interconnect 
	----------------------------------
	Or236260 : entity gtech_lib.or2_d
		generic map(1500 fs)
		port map(
			i0 => i2,
			i1 => i1,
			o0 => Or236260_o0
		);
		Or236280 : entity gtech_lib.or2_d
		generic map(1500 fs)
		port map(
			i0 => i4,
			i1 => i3,
			o0 => Or236280_o0
		);
		Or236300 : entity gtech_lib.or2_d
		generic map(1500 fs)
		port map(
			i0 => i0,
			i1 => i5,
			o0 => Or236300_o0
		);
		Xor236320 : entity gtech_lib.xor2_d
		generic map(2500 fs)
		port map(
			i0 => i3,
			i1 => i4,
			o0 => Xor236320_o0
		);
		Nor236340 : entity gtech_lib.nor2_d
		generic map(2000 fs)
		port map(
			i0 => Or236280_o0,
			i1 => Or236300_o0,
			o0 => Nor236340_o0
		);
		Xor236360 : entity gtech_lib.xor2_d
		generic map(2500 fs)
		port map(
			i0 => Xor236320_o0,
			i1 => Or236260_o0,
			o0 => Xor236360_o0
		);
		And236380 : entity gtech_lib.and2_d
		generic map(1500 fs)
		port map(
			i0 => i5,
			i1 => i2,
			o0 => And236380_o0
		);
		Nor236400 : entity gtech_lib.nor2_d
		generic map(2000 fs)
		port map(
			i0 => Or236260_o0,
			i1 => i0,
			o0 => Nor236400_o0
		);
		Xor236420 : entity gtech_lib.xor2_d
		generic map(2500 fs)
		port map(
			i0 => Xor236360_o0,
			i1 => Nor236400_o0,
			o0 => Xor236420_o0
		);
		Nor236440 : entity gtech_lib.nor2_d
		generic map(2000 fs)
		port map(
			i0 => Nor236340_o0,
			i1 => And236380_o0,
			o0 => Nor236440_o0
		);
		Xor236460 : entity gtech_lib.xor2_d
		generic map(2500 fs)
		port map(
			i0 => i1,
			i1 => i3,
			o0 => Xor236460_o0
		);
		Nand236480 : entity gtech_lib.nand2_d
		generic map(2000 fs)
		port map(
			i0 => Or236280_o0,
			i1 => Nor236400_o0,
			o0 => Nand236480_o0
		);
		Not36500 : entity gtech_lib.not_d
		generic map(1000 fs)
		port map(
			i0 => Nor236440_o0,
			o0 => Not36500_o0
		);
		And236520 : entity gtech_lib.and2_d
		generic map(1500 fs)
		port map(
			i0 => Xor236460_o0,
			i1 => Xor236420_o0,
			o0 => And236520_o0
		);
		Nor236540 : entity gtech_lib.nor2_d
		generic map(2000 fs)
		port map(
			i0 => Nand236480_o0,
			i1 => Nand236480_o0,
			o0 => Nor236540_o0
		);
		Nor236560 : entity gtech_lib.nor2_d
		generic map(2000 fs)
		port map(
			i0 => Nor236340_o0,
			i1 => Xor236320_o0,
			o0 => Nor236560_o0
		);
		Nor236580 : entity gtech_lib.nor2_d
		generic map(2000 fs)
		port map(
			i0 => Nor236540_o0,
			i1 => Not36500_o0,
			o0 => Nor236580_o0
		);
		Or236600 : entity gtech_lib.or2_d
		generic map(1500 fs)
		port map(
			i0 => Nor236560_o0,
			i1 => And236520_o0,
			o0 => Or236600_o0
		);
		Not36620 : entity gtech_lib.not_d
		generic map(1000 fs)
		port map(
			i0 => Nor236540_o0,
			o0 => Not36620_o0
		);
		Nor236640 : entity gtech_lib.nor2_d
		generic map(2000 fs)
		port map(
			i0 => Xor236460_o0,
			i1 => i1,
			o0 => Nor236640_o0
		);
		Or236660 : entity gtech_lib.or2_d
		generic map(1500 fs)
		port map(
			i0 => Nor236640_o0,
			i1 => Not36620_o0,
			o0 => Or236660_o0
		);
		Xor236680 : entity gtech_lib.xor2_d
		generic map(2500 fs)
		port map(
			i0 => Nor236580_o0,
			i1 => Or236600_o0,
			o0 => Xor236680_o0
		);
		And236700 : entity gtech_lib.and2_d
		generic map(1500 fs)
		port map(
			i0 => Xor236420_o0,
			i1 => Not36620_o0,
			o0 => And236700_o0
		);
		Nor236720 : entity gtech_lib.nor2_d
		generic map(2000 fs)
		port map(
			i0 => Or236600_o0,
			i1 => Or236300_o0,
			o0 => Nor236720_o0
		);
		Nor236740 : entity gtech_lib.nor2_d
		generic map(2000 fs)
		port map(
			i0 => Xor236680_o0,
			i1 => Or236660_o0,
			o0 => Nor236740_o0
		);
		Or236760 : entity gtech_lib.or2_d
		generic map(1500 fs)
		port map(
			i0 => And236700_o0,
			i1 => Nor236720_o0,
			o0 => Or236760_o0
		);
		Nor236780 : entity gtech_lib.nor2_d
		generic map(2000 fs)
		port map(
			i0 => Nor236580_o0,
			i1 => Nor236440_o0,
			o0 => Nor236780_o0
		);
		Xor236800 : entity gtech_lib.xor2_d
		generic map(2500 fs)
		port map(
			i0 => Nor236560_o0,
			i1 => Nand236480_o0,
			o0 => Xor236800_o0
		);
		Or236820 : entity gtech_lib.or2_d
		generic map(1500 fs)
		port map(
			i0 => Xor236800_o0,
			i1 => Nor236780_o0,
			o0 => Or236820_o0
		);
		Nand236840 : entity gtech_lib.nand2_d
		generic map(2000 fs)
		port map(
			i0 => Nor236740_o0,
			i1 => Or236760_o0,
			o0 => Nand236840_o0
		);
		And236860 : entity gtech_lib.and2_d
		generic map(1500 fs)
		port map(
			i0 => Xor236320_o0,
			i1 => Nor236640_o0,
			o0 => And236860_o0
		);
		Nor236880 : entity gtech_lib.nor2_d
		generic map(2000 fs)
		port map(
			i0 => Nor236580_o0,
			i1 => Nor236440_o0,
			o0 => Nor236880_o0
		);
		Nor236900 : entity gtech_lib.nor2_d
		generic map(2000 fs)
		port map(
			i0 => And236860_o0,
			i1 => Or236820_o0,
			o0 => Nor236900_o0
		);
		Nor236920 : entity gtech_lib.nor2_d
		generic map(2000 fs)
		port map(
			i0 => Nor236880_o0,
			i1 => Nand236840_o0,
			o0 => Nor236920_o0
		);
		Nand236940 : entity gtech_lib.nand2_d
		generic map(2000 fs)
		port map(
			i0 => Xor236420_o0,
			i1 => Or236600_o0,
			o0 => Nand236940_o0
		);
		Or236960 : entity gtech_lib.or2_d
		generic map(1500 fs)
		port map(
			i0 => And236380_o0,
			i1 => Nor236640_o0,
			o0 => Or236960_o0
		);
		Not36980 : entity gtech_lib.not_d
		generic map(1000 fs)
		port map(
			i0 => Or236960_o0,
			o0 => Not36980_o0
		);
		Nor237000 : entity gtech_lib.nor2_d
		generic map(2000 fs)
		port map(
			i0 => Nand236940_o0,
			i1 => Nor236900_o0,
			o0 => Nor237000_o0
		);
		Nor237020 : entity gtech_lib.nor2_d
		generic map(2000 fs)
		port map(
			i0 => Nor236920_o0,
			i1 => Or236820_o0,
			o0 => Nor237020_o0
		);
		And237040 : entity gtech_lib.and2_d
		generic map(1500 fs)
		port map(
			i0 => Or236260_o0,
			i1 => And236700_o0,
			o0 => And237040_o0
		);
	----------------------------------
	-- Wiring primary ouputs 
	----------------------------------
	o0 <= Nor237020_o0;
	o1 <= And237040_o0;
	o2 <= Not36980_o0;
	o3 <= Nor237000_o0;
end netenos;

tests/tmp/test_1_tb.vhd
library ieee;
use ieee.std_logic_1164.all;
use ieee.numeric_std.all;
-- use ieee.std_logic_textio.all;

library std;
use std.textio.all;

entity test_1_tb is
end entity test_1_tb;

architecture netenos of test_1_tb is

    constant unit_delay : time := 1 ps;
    constant nom_period : time := (unit_delay * 21.0);

    signal tb_in : std_logic_vector(5 downto 0);
    
    signal tb_out : std_logic_vector(3 downto 0);
   

    signal tb_o0 : std_logic; 
	signal tb_o0_s : std_logic;
	signal tb_o1 : std_logic; 
	signal tb_o1_s : std_logic;
	signal tb_o2 : std_logic; 
	signal tb_o2_s : std_logic;
	signal tb_o3 : std_logic; 
	signal tb_o3_s : std_logic;
	

    signal running : boolean := true;
    -- signal phase_shift : boolean := false;

begin

    uut : entity work.test(netenos)
    port map (
               tb_in(0), 
       tb_in(1), 
       tb_in(2), 
       tb_in(3), 
       tb_in(4), 
       tb_in(5), 
       tb_out(0), 
       tb_out(1), 
       tb_out(2), 
       tb_out(3)
    );

    stim : process
       
    begin

        
        wait for 14.0 * unit_delay;
        tb_in(1) <= '1';
    
        wait for 0.0 * unit_delay;
        tb_in(3) <= '1';
    
        wait for 2.5 * unit_delay;
        tb_in(1) <= '1';
    
        wait for 0.5 * unit_delay;
        tb_in(5) <= '0';
    
        wait for 0.0 * unit_delay;
        tb_in(2) <= '0';
     

        wait for nom_period;
        running <= false;
        -- report "Stopping simulation";
        wait;
    end process;

end architecture netenos;

tests/tmp/test_1_tb.vcd
$date
  Tue Sep 17 17:22:51 2024
$end
$version
  GHDL v0
$end
$timescale
  1 fs
$end
$scope module test_1_tb $end
$var reg 6 ! tb_in[5:0] $end
$var reg 4 " tb_out[3:0] $end
$var reg 1 # tb_o0 $end
$var reg 1 $ tb_o0_s $end
$var reg 1 % tb_o1 $end
$var reg 1 & tb_o1_s $end
$var reg 1 ' tb_o2 $end
$var reg 1 ( tb_o2_s $end
$var reg 1 ) tb_o3 $end
$var reg 1 * tb_o3_s $end
$var reg 1 + running $end
$scope module uut $end
$var reg 1 , i0 $end
$var reg 1 - i1 $end
$var reg 1 . i2 $end
$var reg 1 / i3 $end
$var reg 1 0 i4 $end
$var reg 1 1 i5 $end
$var reg 1 2 o0 $end
$var reg 1 3 o1 $end
$var reg 1 4 o2 $end
$var reg 1 5 o3 $end
$var reg 1 6 or236260_o0 $end
$var reg 1 7 or236280_o0 $end
$var reg 1 8 or236300_o0 $end
$var reg 1 9 xor236320_o0 $end
$var reg 1 : nor236340_o0 $end
$var reg 1 ; xor236360_o0 $end
$var reg 1 < and236380_o0 $end
$var reg 1 = nor236400_o0 $end
$var reg 1 > xor236420_o0 $end
$var reg 1 ? nor236440_o0 $end
$var reg 1 @ xor236460_o0 $end
$var reg 1 A nand236480_o0 $end
$var reg 1 B not36500_o0 $end
$var reg 1 C and236520_o0 $end
$var reg 1 D nor236540_o0 $end
$var reg 1 E nor236560_o0 $end
$var reg 1 F nor236580_o0 $end
$var reg 1 G or236600_o0 $end
$var reg 1 H not36620_o0 $end
$var reg 1 I nor236640_o0 $end
$var reg 1 J or236660_o0 $end
$var reg 1 K xor236680_o0 $end
$var reg 1 L and236700_o0 $end
$var reg 1 M nor236720_o0 $end
$var reg 1 N nor236740_o0 $end
$var reg 1 O or236760_o0 $end
$var reg 1 P nor236780_o0 $end
$var reg 1 Q xor236800_o0 $end
$var reg 1 R or236820_o0 $end
$var reg 1 S nand236840_o0 $end
$var reg 1 T and236860_o0 $end
$var reg 1 U nor236880_o0 $end
$var reg 1 V nor236900_o0 $end
$var reg 1 W nor236920_o0 $end
$var reg 1 X nand236940_o0 $end
$var reg 1 Y or236960_o0 $end
$var reg 1 Z not36980_o0 $end
$var reg 1 [ nor237000_o0 $end
$var reg 1 \ nor237020_o0 $end
$var reg 1 ] and237040_o0 $end
$upscope $end
$upscope $end
$enddefinitions $end
#0
bUUUUUU !
bUUUU "
U#
U$
U%
U&
U'
U(
U)
U*
1+
U,
U-
U.
U/
U0
U1
U2
U3
U4
U5
U6
U7
U8
U9
U:
U;
U<
U=
U>
U?
U@
UA
UB
UC
UD
UE
UF
UG
UH
UI
UJ
UK
UL
UM
UN
UO
UP
UQ
UR
US
UT
UU
UV
UW
UX
UY
UZ
U[
U\
U]
#1000
#1500
#2000
#2500
#14000
bUU1U1U !
1-
1/
#15500
16
17
#16000
0I
#16500
0@
#17000
b0U101U !
0.
01
#17500
0:
0=
0T
#18000
0C
#18500
0<
#19500
1A
#20000
0Y
#20500
1?
#21000
bU1UU "
14
1Z
#21500
0B
0D
#22000
#22500
1H
0P
0U
#23500
1F
#24000
1J
#24500
#25500
#26000
0N
#28000
1S
#30000
0W
#32000
#38000
0+
